{
"meta":{"test_sets":[],"test_metrics":[],"learn_metrics":[{"best_value":"Min","name":"Logloss"}],"launch_mode":"Train","parameters":"","iteration_count":1000,"learn_sets":["learn"],"name":"experiment"},
"iterations":[
{"learn":[0.6652411515],"iteration":0,"passed_time":0.05724641002,"remaining_time":57.18916361},
{"learn":[0.6395992226],"iteration":1,"passed_time":0.103545813,"remaining_time":51.66936066},
{"learn":[0.6166275262],"iteration":2,"passed_time":0.1495354233,"remaining_time":49.69560569},
{"learn":[0.5939262811],"iteration":3,"passed_time":0.1975246523,"remaining_time":49.18363842},
{"learn":[0.5735675023],"iteration":4,"passed_time":0.2426012224,"remaining_time":48.27764326},
{"learn":[0.5538144273],"iteration":5,"passed_time":0.2876898018,"remaining_time":47.6606105},
{"learn":[0.5356129923],"iteration":6,"passed_time":0.3337307571,"remaining_time":47.34209169},
{"learn":[0.5177594449],"iteration":7,"passed_time":0.3791563224,"remaining_time":47.01538398},
{"learn":[0.5011366814],"iteration":8,"passed_time":0.4242711804,"remaining_time":46.71697109},
{"learn":[0.4863323847],"iteration":9,"passed_time":0.4690217623,"remaining_time":46.43315447},
{"learn":[0.4724047513],"iteration":10,"passed_time":0.5138187952,"remaining_time":46.19698076},
{"learn":[0.4595170547],"iteration":11,"passed_time":0.5587389283,"remaining_time":46.00283843},
{"learn":[0.4477422938],"iteration":12,"passed_time":0.6033350793,"remaining_time":45.80705564},
{"learn":[0.4363434006],"iteration":13,"passed_time":0.6504797403,"remaining_time":45.81235885},
{"learn":[0.4257681576],"iteration":14,"passed_time":0.6979853901,"remaining_time":45.83437395},
{"learn":[0.4154025958],"iteration":15,"passed_time":0.7415360865,"remaining_time":45.60446932},
{"learn":[0.4059343944],"iteration":16,"passed_time":0.7860902963,"remaining_time":45.45451537},
{"learn":[0.3971458443],"iteration":17,"passed_time":0.8309150148,"remaining_time":45.33103025},
{"learn":[0.3894920786],"iteration":18,"passed_time":0.875564426,"remaining_time":45.20677379},
{"learn":[0.3822262398],"iteration":19,"passed_time":0.918916981,"remaining_time":45.02693207},
{"learn":[0.3750199858],"iteration":20,"passed_time":0.96403424,"remaining_time":44.94235814},
{"learn":[0.3682906121],"iteration":21,"passed_time":1.010921877,"remaining_time":44.94007255},
{"learn":[0.3617943605],"iteration":22,"passed_time":1.058650264,"remaining_time":44.9696221},
{"learn":[0.355763235],"iteration":23,"passed_time":1.103986724,"remaining_time":44.8954601},
{"learn":[0.3499252939],"iteration":24,"passed_time":1.148462264,"remaining_time":44.79002828},
{"learn":[0.3444019422],"iteration":25,"passed_time":1.194325969,"remaining_time":44.74128824},
{"learn":[0.3396184021],"iteration":26,"passed_time":1.238526735,"remaining_time":44.63283383},
{"learn":[0.3349815711],"iteration":27,"passed_time":1.28324294,"remaining_time":44.54686207},
{"learn":[0.3303636757],"iteration":28,"passed_time":1.328158092,"remaining_time":44.47039681},
{"learn":[0.3264994805],"iteration":29,"passed_time":1.373125509,"remaining_time":44.3977248},
{"learn":[0.3223873942],"iteration":30,"passed_time":1.418361491,"remaining_time":44.33523498},
{"learn":[0.3186398277],"iteration":31,"passed_time":1.46296765,"remaining_time":44.25477141},
{"learn":[0.3149656326],"iteration":32,"passed_time":1.50764482,"remaining_time":44.17856183},
{"learn":[0.3119361307],"iteration":33,"passed_time":1.553286045,"remaining_time":44.13159764},
{"learn":[0.3087400356],"iteration":34,"passed_time":1.598224151,"remaining_time":44.06532302},
{"learn":[0.306097004],"iteration":35,"passed_time":1.643803907,"remaining_time":44.01741574},
{"learn":[0.3032713567],"iteration":36,"passed_time":1.691746064,"remaining_time":44.03112054},
{"learn":[0.3004608173],"iteration":37,"passed_time":1.741572988,"remaining_time":44.08929513},
{"learn":[0.2980294992],"iteration":38,"passed_time":1.790554748,"remaining_time":44.12110546},
{"learn":[0.2955852073],"iteration":39,"passed_time":1.837704004,"remaining_time":44.10489611},
{"learn":[0.2935463892],"iteration":40,"passed_time":1.88293752,"remaining_time":44.04236784},
{"learn":[0.2916220318],"iteration":41,"passed_time":1.928801005,"remaining_time":43.99503245},
{"learn":[0.2896542816],"iteration":42,"passed_time":1.974602299,"remaining_time":43.94638139},
{"learn":[0.2878078687],"iteration":43,"passed_time":2.021264481,"remaining_time":43.91656463},
{"learn":[0.2860944796],"iteration":44,"passed_time":2.066803333,"remaining_time":43.86215961},
{"learn":[0.2843940983],"iteration":45,"passed_time":2.112302746,"remaining_time":43.80732217},
{"learn":[0.2828793473],"iteration":46,"passed_time":2.159660345,"remaining_time":43.79055976},
{"learn":[0.2814019764],"iteration":47,"passed_time":2.205328446,"remaining_time":43.73901418},
{"learn":[0.280030835],"iteration":48,"passed_time":2.25106669,"remaining_time":43.68906985},
{"learn":[0.2786867759],"iteration":49,"passed_time":2.297761217,"remaining_time":43.65746313},
{"learn":[0.2773149739],"iteration":50,"passed_time":2.343369903,"remaining_time":43.60505958},
{"learn":[0.276185406],"iteration":51,"passed_time":2.390030836,"remaining_time":43.57210062},
{"learn":[0.2750188137],"iteration":52,"passed_time":2.436431831,"remaining_time":43.53398008},
{"learn":[0.2740853434],"iteration":53,"passed_time":2.481186206,"remaining_time":43.4667065},
{"learn":[0.2729756766],"iteration":54,"passed_time":2.527708518,"remaining_time":43.43062818},
{"learn":[0.2718803555],"iteration":55,"passed_time":2.57288864,"remaining_time":43.37155136},
{"learn":[0.2709261203],"iteration":56,"passed_time":2.618632841,"remaining_time":43.32229419},
{"learn":[0.26998618],"iteration":57,"passed_time":2.663765215,"remaining_time":43.26322126},
{"learn":[0.2692615778],"iteration":58,"passed_time":2.709584623,"remaining_time":43.21557848},
{"learn":[0.2684727163],"iteration":59,"passed_time":2.758442215,"remaining_time":43.2155947},
{"learn":[0.2676835668],"iteration":60,"passed_time":2.805374898,"remaining_time":43.18437754},
{"learn":[0.2669033601],"iteration":61,"passed_time":2.851188842,"remaining_time":43.13572797},
{"learn":[0.2662581251],"iteration":62,"passed_time":2.897912229,"remaining_time":43.10069458},
{"learn":[0.2656113487],"iteration":63,"passed_time":2.944527919,"remaining_time":43.06372081},
{"learn":[0.2650597926],"iteration":64,"passed_time":2.991440454,"remaining_time":43.03072037},
{"learn":[0.2645215491],"iteration":65,"passed_time":3.037429469,"remaining_time":42.98422915},
{"learn":[0.2639456545],"iteration":66,"passed_time":3.084636691,"remaining_time":42.9547169},
{"learn":[0.2633988238],"iteration":67,"passed_time":3.130818275,"remaining_time":42.91062694},
{"learn":[0.2627797396],"iteration":68,"passed_time":3.177365489,"remaining_time":42.87140972},
{"learn":[0.2622916299],"iteration":69,"passed_time":3.223961051,"remaining_time":42.8326254},
{"learn":[0.2619235871],"iteration":70,"passed_time":3.269501802,"remaining_time":42.77981936},
{"learn":[0.2614761263],"iteration":71,"passed_time":3.315264604,"remaining_time":42.73007712},
{"learn":[0.2610369478],"iteration":72,"passed_time":3.365479348,"remaining_time":42.73697748},
{"learn":[0.2606415347],"iteration":73,"passed_time":3.413863847,"remaining_time":42.71943138},
{"learn":[0.2602196489],"iteration":74,"passed_time":3.460454972,"remaining_time":42.67894465},
{"learn":[0.2598494043],"iteration":75,"passed_time":3.506253693,"remaining_time":42.62866333},
{"learn":[0.259471521],"iteration":76,"passed_time":3.552067339,"remaining_time":42.57867732},
{"learn":[0.2591575753],"iteration":77,"passed_time":3.598205639,"remaining_time":42.53263589},
{"learn":[0.2587757965],"iteration":78,"passed_time":3.643836595,"remaining_time":42.48067726},
{"learn":[0.258434057],"iteration":79,"passed_time":3.690593837,"remaining_time":42.44182913},
{"learn":[0.2581493447],"iteration":80,"passed_time":3.737072351,"remaining_time":42.39962334},
{"learn":[0.2578045396],"iteration":81,"passed_time":3.785205609,"remaining_time":42.37583841},
{"learn":[0.2575580712],"iteration":82,"passed_time":3.834606031,"remaining_time":42.36546663},
{"learn":[0.2572058815],"iteration":83,"passed_time":3.88209512,"remaining_time":42.33332298},
{"learn":[0.2569620383],"iteration":84,"passed_time":3.92831983,"remaining_time":42.28720758},
{"learn":[0.2566646909],"iteration":85,"passed_time":3.97377279,"remaining_time":42.23288756},
{"learn":[0.2563860251],"iteration":86,"passed_time":4.020240874,"remaining_time":42.18942435},
{"learn":[0.2561242117],"iteration":87,"passed_time":4.065558792,"remaining_time":42.13397294},
{"learn":[0.2558665479],"iteration":88,"passed_time":4.111598045,"remaining_time":42.0861328},
{"learn":[0.2556224337],"iteration":89,"passed_time":4.159090134,"remaining_time":42.05302247},
{"learn":[0.2553998296],"iteration":90,"passed_time":4.205192798,"remaining_time":42.00571707},
{"learn":[0.25518544],"iteration":91,"passed_time":4.250079273,"remaining_time":41.94643456},
{"learn":[0.2550054158],"iteration":92,"passed_time":4.296793285,"remaining_time":41.90528505},
{"learn":[0.2548277797],"iteration":93,"passed_time":4.342389971,"remaining_time":41.85324802},
{"learn":[0.2546427082],"iteration":94,"passed_time":4.390389888,"remaining_time":41.82424052},
{"learn":[0.2544749972],"iteration":95,"passed_time":4.434748122,"remaining_time":41.76054482},
{"learn":[0.2543579281],"iteration":96,"passed_time":4.481297858,"remaining_time":41.71764913},
{"learn":[0.2542300531],"iteration":97,"passed_time":4.527397716,"remaining_time":41.67053816},
{"learn":[0.2540516379],"iteration":98,"passed_time":4.576444914,"remaining_time":41.65027138},
{"learn":[0.2539351616],"iteration":99,"passed_time":4.622344309,"remaining_time":41.60109878},
{"learn":[0.2537855564],"iteration":100,"passed_time":4.667994108,"remaining_time":41.54976934},
{"learn":[0.2536326484],"iteration":101,"passed_time":4.713775584,"remaining_time":41.49971053},
{"learn":[0.2535109046],"iteration":102,"passed_time":4.759677207,"remaining_time":41.45078112},
{"learn":[0.2533598597],"iteration":103,"passed_time":4.805523791,"remaining_time":41.40143574},
{"learn":[0.253224109],"iteration":104,"passed_time":4.851063206,"remaining_time":41.34953875},
{"learn":[0.2530955566],"iteration":105,"passed_time":4.897520399,"remaining_time":41.30550223},
{"learn":[0.2530032664],"iteration":106,"passed_time":4.943724893,"remaining_time":41.25931149},
{"learn":[0.2528590302],"iteration":107,"passed_time":4.990034889,"remaining_time":41.21399186},
{"learn":[0.2527469914],"iteration":108,"passed_time":5.035893631,"remaining_time":41.16496537},
{"learn":[0.2526105971],"iteration":109,"passed_time":5.081767565,"remaining_time":41.11611939},
{"learn":[0.2524643962],"iteration":110,"passed_time":5.126696194,"remaining_time":41.05975601},
{"learn":[0.2523644166],"iteration":111,"passed_time":5.173936634,"remaining_time":41.02192617},
{"learn":[0.2522637765],"iteration":112,"passed_time":5.220775748,"remaining_time":40.98077954},
{"learn":[0.2521837149],"iteration":113,"passed_time":5.266813629,"remaining_time":40.93330592},
{"learn":[0.252075741],"iteration":114,"passed_time":5.313427391,"remaining_time":40.89028905},
{"learn":[0.2520010315],"iteration":115,"passed_time":5.36391162,"remaining_time":40.87670579},
{"learn":[0.2518795757],"iteration":116,"passed_time":5.412563784,"remaining_time":40.84866514},
{"learn":[0.251785812],"iteration":117,"passed_time":5.458151493,"remaining_time":40.79736964},
{"learn":[0.251698078],"iteration":118,"passed_time":5.502916715,"remaining_time":40.74008089},
{"learn":[0.2515681197],"iteration":119,"passed_time":5.54932313,"remaining_time":40.69503629},
{"learn":[0.2514780991],"iteration":120,"passed_time":5.595000818,"remaining_time":40.64467536},
{"learn":[0.2513947856],"iteration":121,"passed_time":5.643744426,"remaining_time":40.61645578},
{"learn":[0.2513180437],"iteration":122,"passed_time":5.693121549,"remaining_time":40.5924195},
{"learn":[0.2512560032],"iteration":123,"passed_time":5.742525994,"remaining_time":40.56816751},
{"learn":[0.2511794306],"iteration":124,"passed_time":5.791230692,"remaining_time":40.53861484},
{"learn":[0.2511117162],"iteration":125,"passed_time":5.83649986,"remaining_time":40.4849276},
{"learn":[0.2510117366],"iteration":126,"passed_time":5.881831758,"remaining_time":40.43180413},
{"learn":[0.2509796916],"iteration":127,"passed_time":5.927066946,"remaining_time":40.37814357},
{"learn":[0.250882134],"iteration":128,"passed_time":5.973774039,"remaining_time":40.33455184},
{"learn":[0.2508282064],"iteration":129,"passed_time":6.023127075,"remaining_time":40.30861966},
{"learn":[0.2507523452],"iteration":130,"passed_time":6.068758098,"remaining_time":40.2576396},
{"learn":[0.2506801424],"iteration":131,"passed_time":6.114708273,"remaining_time":40.20883925},
{"learn":[0.2506305167],"iteration":132,"passed_time":6.161839313,"remaining_time":40.16777958},
{"learn":[0.2505624636],"iteration":133,"passed_time":6.208255273,"remaining_time":40.12200796},
{"learn":[0.2505142267],"iteration":134,"passed_time":6.254598251,"remaining_time":40.07575916},
{"learn":[0.2504600111],"iteration":135,"passed_time":6.300203783,"remaining_time":40.02482403},
{"learn":[0.250395701],"iteration":136,"passed_time":6.347132838,"remaining_time":39.98230394},
{"learn":[0.2503223804],"iteration":137,"passed_time":6.39307355,"remaining_time":39.93354637},
{"learn":[0.2502533787],"iteration":138,"passed_time":6.438632092,"remaining_time":39.8824621},
{"learn":[0.2501983671],"iteration":139,"passed_time":6.485544205,"remaining_time":39.83977155},
{"learn":[0.2501424578],"iteration":140,"passed_time":6.531415685,"remaining_time":39.79068137},
{"learn":[0.2500973543],"iteration":141,"passed_time":6.578215762,"remaining_time":39.74724735},
{"learn":[0.2500377019],"iteration":142,"passed_time":6.624325618,"remaining_time":39.69962975},
{"learn":[0.249985468],"iteration":143,"passed_time":6.670644079,"remaining_time":39.65327313},
{"learn":[0.2499319637],"iteration":144,"passed_time":6.716125539,"remaining_time":39.60198163},
{"learn":[0.2498740728],"iteration":145,"passed_time":6.764279439,"remaining_time":39.56640165},
{"learn":[0.2498199588],"iteration":146,"passed_time":6.811755772,"remaining_time":39.52671887},
{"learn":[0.2497769556],"iteration":147,"passed_time":6.861426813,"remaining_time":39.49956517},
{"learn":[0.2497292269],"iteration":148,"passed_time":6.907558648,"remaining_time":39.45189536},
{"learn":[0.2496559062],"iteration":149,"passed_time":6.953839938,"remaining_time":39.40509298},
{"learn":[0.2496031642],"iteration":150,"passed_time":6.999880417,"remaining_time":39.35694354},
{"learn":[0.2495470347],"iteration":151,"passed_time":7.04531979,"remaining_time":39.3054683},
{"learn":[0.2495163108],"iteration":152,"passed_time":7.090639979,"remaining_time":39.25341217},
{"learn":[0.2494658722],"iteration":153,"passed_time":7.135232521,"remaining_time":39.19744619},
{"learn":[0.249419888],"iteration":154,"passed_time":7.181220354,"remaining_time":39.14923354},
{"learn":[0.2493717867],"iteration":155,"passed_time":7.229848798,"remaining_time":39.1153358},
{"learn":[0.2493196713],"iteration":156,"passed_time":7.278007062,"remaining_time":39.07872582},
{"learn":[0.2492674204],"iteration":157,"passed_time":7.324005233,"remaining_time":39.03045826},
{"learn":[0.2492266867],"iteration":158,"passed_time":7.371232234,"remaining_time":38.98871892},
{"learn":[0.2491652051],"iteration":159,"passed_time":7.416892896,"remaining_time":38.93868771},
{"learn":[0.2491013015],"iteration":160,"passed_time":7.462973031,"remaining_time":38.89089673},
{"learn":[0.2490727286],"iteration":161,"passed_time":7.507860073,"remaining_time":38.83695519},
{"learn":[0.249029827],"iteration":162,"passed_time":7.549450775,"remaining_time":38.76619815},
{"learn":[0.248996732],"iteration":163,"passed_time":7.594735879,"remaining_time":38.71462924},
{"learn":[0.2489609439],"iteration":164,"passed_time":7.640690078,"remaining_time":38.66652252},
{"learn":[0.2489157896],"iteration":165,"passed_time":7.688878539,"remaining_time":38.62966688},
{"learn":[0.2488763771],"iteration":166,"passed_time":7.736604886,"remaining_time":38.59037048},
{"learn":[0.2488395728],"iteration":167,"passed_time":7.785590421,"remaining_time":38.5572097},
{"learn":[0.2487774476],"iteration":168,"passed_time":7.831671641,"remaining_time":38.50958067},
{"learn":[0.2487516693],"iteration":169,"passed_time":7.878171425,"remaining_time":38.46401343},
{"learn":[0.2487178798],"iteration":170,"passed_time":7.926846183,"remaining_time":38.42897945},
{"learn":[0.2486833621],"iteration":171,"passed_time":7.975639941,"remaining_time":38.39435972},
{"learn":[0.2486551618],"iteration":172,"passed_time":8.025445532,"remaining_time":38.36441304},
{"learn":[0.2486243871],"iteration":173,"passed_time":8.069843447,"remaining_time":38.30856717},
{"learn":[0.2485982871],"iteration":174,"passed_time":8.116121882,"remaining_time":38.26171745},
{"learn":[0.2485740332],"iteration":175,"passed_time":8.162713318,"remaining_time":38.21633963},
{"learn":[0.2485397695],"iteration":176,"passed_time":8.207463475,"remaining_time":38.16238667},
{"learn":[0.2485235099],"iteration":177,"passed_time":8.259308567,"remaining_time":38.14130136},
{"learn":[0.2484905842],"iteration":178,"passed_time":8.307952745,"remaining_time":38.10519108},
{"learn":[0.2484712929],"iteration":179,"passed_time":8.353789536,"remaining_time":38.05615233},
{"learn":[0.2484301527],"iteration":180,"passed_time":8.399622447,"remaining_time":38.0071314},
{"learn":[0.2484124026],"iteration":181,"passed_time":8.447982731,"remaining_time":37.9695048},
{"learn":[0.2483810182],"iteration":182,"passed_time":8.49398072,"remaining_time":37.92121447},
{"learn":[0.2483567474],"iteration":183,"passed_time":8.539072762,"remaining_time":37.86893138},
{"learn":[0.2483303425],"iteration":184,"passed_time":8.584921903,"remaining_time":37.82006136},
{"learn":[0.2482984161],"iteration":185,"passed_time":8.630069515,"remaining_time":37.76815369},
{"learn":[0.2482644064],"iteration":186,"passed_time":8.675586615,"remaining_time":37.71792469},
{"learn":[0.2482273311],"iteration":187,"passed_time":8.721154856,"remaining_time":37.66796672},
{"learn":[0.2481996729],"iteration":188,"passed_time":8.768046927,"remaining_time":37.62373576},
{"learn":[0.2481710323],"iteration":189,"passed_time":8.81746414,"remaining_time":37.59024186},
{"learn":[0.2481438483],"iteration":190,"passed_time":8.86341002,"remaining_time":37.54187804},
{"learn":[0.2480988634],"iteration":191,"passed_time":8.908576337,"remaining_time":37.49025875},
{"learn":[0.2480857371],"iteration":192,"passed_time":8.954552323,"remaining_time":37.44209184},
{"learn":[0.2480639222],"iteration":193,"passed_time":9.000302371,"remaining_time":37.39300882},
{"learn":[0.2480288963],"iteration":194,"passed_time":9.050602295,"remaining_time":37.36274281},
{"learn":[0.2480042867],"iteration":195,"passed_time":9.099508788,"remaining_time":37.32655646},
{"learn":[0.247963841],"iteration":196,"passed_time":9.146684373,"remaining_time":37.28318554},
{"learn":[0.2479410775],"iteration":197,"passed_time":9.196078011,"remaining_time":37.24876043},
{"learn":[0.2479123522],"iteration":198,"passed_time":9.242077612,"remaining_time":37.20052345},
{"learn":[0.2478974307],"iteration":199,"passed_time":9.288988235,"remaining_time":37.15595294},
{"learn":[0.2478492955],"iteration":200,"passed_time":9.334603869,"remaining_time":37.1062114},
{"learn":[0.2478189103],"iteration":201,"passed_time":9.38129272,"remaining_time":37.06075045},
{"learn":[0.2478047509],"iteration":202,"passed_time":9.429562905,"remaining_time":37.02148589},
{"learn":[0.2477713002],"iteration":203,"passed_time":9.478166169,"remaining_time":36.9834327},
{"learn":[0.2477491465],"iteration":204,"passed_time":9.529519833,"remaining_time":36.95594277},
{"learn":[0.2477228093],"iteration":205,"passed_time":9.575423138,"remaining_time":36.90721346},
{"learn":[0.2476804328],"iteration":206,"passed_time":9.622220417,"remaining_time":36.86193619},
{"learn":[0.2476597865],"iteration":207,"passed_time":9.667576878,"remaining_time":36.81115811},
{"learn":[0.2476357866],"iteration":208,"passed_time":9.713200741,"remaining_time":36.76144395},
{"learn":[0.2476133958],"iteration":209,"passed_time":9.760126603,"remaining_time":36.71666675},
{"learn":[0.2475887015],"iteration":210,"passed_time":9.805196408,"remaining_time":36.66492875},
{"learn":[0.2475669374],"iteration":211,"passed_time":9.851613525,"remaining_time":36.61826159},
{"learn":[0.2475296758],"iteration":212,"passed_time":9.895437284,"remaining_time":36.56201475},
{"learn":[0.2475074882],"iteration":213,"passed_time":9.940904781,"remaining_time":36.5119213},
{"learn":[0.247482794],"iteration":214,"passed_time":9.986653827,"remaining_time":36.46289886},
{"learn":[0.2474513418],"iteration":215,"passed_time":10.032301,"remaining_time":36.41353695},
{"learn":[0.2474196017],"iteration":216,"passed_time":10.07779183,"remaining_time":36.36364519},
{"learn":[0.2473895214],"iteration":217,"passed_time":10.12680045,"remaining_time":36.32641261},
{"learn":[0.2473715173],"iteration":218,"passed_time":10.17688496,"remaining_time":36.29290937},
{"learn":[0.2473451463],"iteration":219,"passed_time":10.2226251,"remaining_time":36.24385264},
{"learn":[0.2473248218],"iteration":220,"passed_time":10.27226682,"remaining_time":36.20857852},
{"learn":[0.2473042771],"iteration":221,"passed_time":10.31791249,"remaining_time":36.15917079},
{"learn":[0.2472692004],"iteration":222,"passed_time":10.36361896,"remaining_time":36.11000866},
{"learn":[0.2472563621],"iteration":223,"passed_time":10.40711946,"remaining_time":36.05323527},
{"learn":[0.247234852],"iteration":224,"passed_time":10.45271134,"remaining_time":36.00378351},
{"learn":[0.2472146122],"iteration":225,"passed_time":10.49737822,"remaining_time":35.95119799},
{"learn":[0.2471870217],"iteration":226,"passed_time":10.54323437,"remaining_time":35.90273201},
{"learn":[0.2471794508],"iteration":227,"passed_time":10.59239786,"remaining_time":35.86548748},
{"learn":[0.2471563995],"iteration":228,"passed_time":10.63716366,"remaining_time":35.81333267},
{"learn":[0.2471374807],"iteration":229,"passed_time":10.67974517,"remaining_time":35.75392949},
{"learn":[0.2471194427],"iteration":230,"passed_time":10.72608086,"remaining_time":35.70716961},
{"learn":[0.2471105846],"iteration":231,"passed_time":10.76522679,"remaining_time":35.63661281},
{"learn":[0.2470996941],"iteration":232,"passed_time":10.80958636,"remaining_time":35.58348816},
{"learn":[0.2470767952],"iteration":233,"passed_time":10.85507459,"remaining_time":35.53413305},
{"learn":[0.2470622462],"iteration":234,"passed_time":10.90172914,"remaining_time":35.48860762},
{"learn":[0.2470357905],"iteration":235,"passed_time":10.95077367,"remaining_time":35.45080969},
{"learn":[0.2470034576],"iteration":236,"passed_time":10.99883873,"remaining_time":35.40976349},
{"learn":[0.2469961577],"iteration":237,"passed_time":11.05237687,"remaining_time":35.38618141},
{"learn":[0.2469644854],"iteration":238,"passed_time":11.10117053,"remaining_time":35.34724173},
{"learn":[0.2469474128],"iteration":239,"passed_time":11.14815731,"remaining_time":35.30249815},
{"learn":[0.2469314581],"iteration":240,"passed_time":11.19545727,"remaining_time":35.25872227},
{"learn":[0.2469122175],"iteration":241,"passed_time":11.2404663,"remaining_time":35.20774154},
{"learn":[0.2468984138],"iteration":242,"passed_time":11.28635004,"remaining_time":35.15953489},
{"learn":[0.2468866256],"iteration":243,"passed_time":11.33499709,"remaining_time":35.11990901},
{"learn":[0.2468694853],"iteration":244,"passed_time":11.38454204,"remaining_time":35.0829765},
{"learn":[0.2468521587],"iteration":245,"passed_time":11.43289653,"remaining_time":35.04229262},
{"learn":[0.246838609],"iteration":246,"passed_time":11.47794599,"remaining_time":34.99147097},
{"learn":[0.2468221631],"iteration":247,"passed_time":11.52315872,"remaining_time":34.94119094},
{"learn":[0.2467998908],"iteration":248,"passed_time":11.57138424,"remaining_time":34.90003841},
{"learn":[0.246781006],"iteration":249,"passed_time":11.6171803,"remaining_time":34.8515409},
{"learn":[0.2467677273],"iteration":250,"passed_time":11.66202101,"remaining_time":34.80021409},
{"learn":[0.2467495369],"iteration":251,"passed_time":11.70767539,"remaining_time":34.75135394},
{"learn":[0.2467232675],"iteration":252,"passed_time":11.75481942,"remaining_time":34.70691743},
{"learn":[0.2467060255],"iteration":253,"passed_time":11.80316406,"remaining_time":34.66598579},
{"learn":[0.2466866326],"iteration":254,"passed_time":11.84929319,"remaining_time":34.61852323},
{"learn":[0.2466621923],"iteration":255,"passed_time":11.89405267,"remaining_time":34.56709057},
{"learn":[0.2466463392],"iteration":256,"passed_time":11.94182989,"remaining_time":34.52443429},
{"learn":[0.2466357874],"iteration":257,"passed_time":11.98653209,"remaining_time":34.47289461},
{"learn":[0.2466160219],"iteration":258,"passed_time":12.03569597,"remaining_time":34.43417264},
{"learn":[0.2465994913],"iteration":259,"passed_time":12.08212747,"remaining_time":34.38759358},
{"learn":[0.246590955],"iteration":260,"passed_time":12.13008966,"remaining_time":34.34534965},
{"learn":[0.2465724597],"iteration":261,"passed_time":12.1752319,"remaining_time":34.29511885},
{"learn":[0.2465590624],"iteration":262,"passed_time":12.22329225,"remaining_time":34.25310413},
{"learn":[0.2465362143],"iteration":263,"passed_time":12.27185292,"remaining_time":34.21243844},
{"learn":[0.246523376],"iteration":264,"passed_time":12.32002342,"remaining_time":34.17063101},
{"learn":[0.2465146873],"iteration":265,"passed_time":12.36930418,"remaining_time":34.13183936},
{"learn":[0.2465005787],"iteration":266,"passed_time":12.41466662,"remaining_time":34.08221212},
{"learn":[0.2464844038],"iteration":267,"passed_time":12.46167495,"remaining_time":34.03711219},
{"learn":[0.2464662981],"iteration":268,"passed_time":12.50828341,"remaining_time":33.99091141},
{"learn":[0.2464480399],"iteration":269,"passed_time":12.55926911,"remaining_time":33.95654242},
{"learn":[0.2464327457],"iteration":270,"passed_time":12.60243366,"remaining_time":33.90101157},
{"learn":[0.246421076],"iteration":271,"passed_time":12.65655575,"remaining_time":33.8748992},
{"learn":[0.2464077127],"iteration":272,"passed_time":12.70190209,"remaining_time":33.82521179},
{"learn":[0.2463931299],"iteration":273,"passed_time":12.74738621,"remaining_time":33.77592113},
{"learn":[0.2463726699],"iteration":274,"passed_time":12.79367285,"remaining_time":33.72877388},
{"learn":[0.2463492798],"iteration":275,"passed_time":12.83947947,"remaining_time":33.68037368},
{"learn":[0.2463189116],"iteration":276,"passed_time":12.88530663,"remaining_time":33.63204584},
{"learn":[0.2463121198],"iteration":277,"passed_time":12.93372641,"remaining_time":33.59046932},
{"learn":[0.2463015002],"iteration":278,"passed_time":12.97994483,"remaining_time":33.54315491},
{"learn":[0.2462893394],"iteration":279,"passed_time":13.02554889,"remaining_time":33.49426858},
{"learn":[0.2462717418],"iteration":280,"passed_time":13.07177506,"remaining_time":33.44699738},
{"learn":[0.246252315],"iteration":281,"passed_time":13.11750323,"remaining_time":33.39846567},
{"learn":[0.2462416446],"iteration":282,"passed_time":13.15686806,"remaining_time":33.3338318},
{"learn":[0.2462356827],"iteration":283,"passed_time":13.20607365,"remaining_time":33.29418568},
{"learn":[0.2462233526],"iteration":284,"passed_time":13.25400616,"remaining_time":33.2512786},
{"learn":[0.2462175093],"iteration":285,"passed_time":13.30302167,"remaining_time":33.21104011},
{"learn":[0.2461985397],"iteration":286,"passed_time":13.34910463,"remaining_time":33.16345505},
{"learn":[0.2461817212],"iteration":287,"passed_time":13.39535637,"remaining_time":33.11629769},
{"learn":[0.2461705258],"iteration":288,"passed_time":13.44170241,"remaining_time":33.06937859},
{"learn":[0.2461573826],"iteration":289,"passed_time":13.48845357,"remaining_time":33.02345529},
{"learn":[0.2461510312],"iteration":290,"passed_time":13.53553142,"remaining_time":32.97832225},
{"learn":[0.2461402423],"iteration":291,"passed_time":13.58280723,"remaining_time":32.93365589},
{"learn":[0.2461293009],"iteration":292,"passed_time":13.62817014,"remaining_time":32.88435593},
{"learn":[0.2461046914],"iteration":293,"passed_time":13.67409462,"remaining_time":32.8364313},
{"learn":[0.2460921071],"iteration":294,"passed_time":13.71907634,"remaining_time":32.78626717},
{"learn":[0.2460678532],"iteration":295,"passed_time":13.7641373,"remaining_time":32.73632654},
{"learn":[0.24605471],"iteration":296,"passed_time":13.805404,"remaining_time":32.67743776},
{"learn":[0.2460485788],"iteration":297,"passed_time":13.85118989,"remaining_time":32.6293131},
{"learn":[0.2460389924],"iteration":298,"passed_time":13.89863233,"remaining_time":32.58508783},
{"learn":[0.246020531],"iteration":299,"passed_time":13.9473389,"remaining_time":32.54379076},
{"learn":[0.2460141288],"iteration":300,"passed_time":13.99411335,"remaining_time":32.49795757},
{"learn":[0.2460044408],"iteration":301,"passed_time":14.04039934,"remaining_time":32.4509892},
{"learn":[0.24597934],"iteration":302,"passed_time":14.08668504,"remaining_time":32.40402466},
{"learn":[0.2459679244],"iteration":303,"passed_time":14.13212585,"remaining_time":32.35513023},
{"learn":[0.2459578977],"iteration":304,"passed_time":14.18132597,"remaining_time":32.31482476},
{"learn":[0.2459540699],"iteration":305,"passed_time":14.22882341,"remaining_time":32.27059949},
{"learn":[0.245944077],"iteration":306,"passed_time":14.27721019,"remaining_time":32.22836047},
{"learn":[0.2459311371],"iteration":307,"passed_time":14.32307214,"remaining_time":32.18040883},
{"learn":[0.2459058331],"iteration":308,"passed_time":14.37002708,"remaining_time":32.13491493},
{"learn":[0.2458929609],"iteration":309,"passed_time":14.4163628,"remaining_time":32.08803332},
{"learn":[0.2458769554],"iteration":310,"passed_time":14.46897533,"remaining_time":32.05506109},
{"learn":[0.245868978],"iteration":311,"passed_time":14.51711378,"remaining_time":32.01209706},
{"learn":[0.245857122],"iteration":312,"passed_time":14.56830602,"remaining_time":31.97580266},
{"learn":[0.2458438772],"iteration":313,"passed_time":14.61350123,"remaining_time":31.9263116},
{"learn":[0.2458372887],"iteration":314,"passed_time":14.65957324,"remaining_time":31.87875451},
{"learn":[0.2458306832],"iteration":315,"passed_time":14.70827883,"remaining_time":31.83690733},
{"learn":[0.2458203347],"iteration":316,"passed_time":14.75996036,"remaining_time":31.80142878},
{"learn":[0.2458126114],"iteration":317,"passed_time":14.80937176,"remaining_time":31.76097968},
{"learn":[0.2458045493],"iteration":318,"passed_time":14.85880206,"remaining_time":31.72051474},
{"learn":[0.2457888317],"iteration":319,"passed_time":14.90433399,"remaining_time":31.67170973},
{"learn":[0.2457794824],"iteration":320,"passed_time":14.94987166,"remaining_time":31.62293724},
{"learn":[0.2457660344],"iteration":321,"passed_time":14.99500059,"remaining_time":31.57332423},
{"learn":[0.2457567529],"iteration":322,"passed_time":15.04341378,"remaining_time":31.53062269},
{"learn":[0.2457350565],"iteration":323,"passed_time":15.09360139,"remaining_time":31.4915881},
{"learn":[0.2457159006],"iteration":324,"passed_time":15.14750132,"remaining_time":31.46019505},
{"learn":[0.245702334],"iteration":325,"passed_time":15.19518461,"remaining_time":31.41581113},
{"learn":[0.245677301],"iteration":326,"passed_time":15.24037207,"remaining_time":31.36627034},
{"learn":[0.2456620577],"iteration":327,"passed_time":15.28601786,"remaining_time":31.31769514},
{"learn":[0.2456547916],"iteration":328,"passed_time":15.33996254,"remaining_time":31.28606341},
{"learn":[0.2456425123],"iteration":329,"passed_time":15.38749274,"remaining_time":31.24127314},
{"learn":[0.2456331799],"iteration":330,"passed_time":15.43149579,"remaining_time":31.18933742},
{"learn":[0.2456267947],"iteration":331,"passed_time":15.47802908,"remaining_time":31.14254044},
{"learn":[0.2456060129],"iteration":332,"passed_time":15.52298951,"remaining_time":31.09259461},
{"learn":[0.2455892282],"iteration":333,"passed_time":15.56741254,"remaining_time":31.04160704},
{"learn":[0.2455797265],"iteration":334,"passed_time":15.60872694,"remaining_time":30.98448781},
{"learn":[0.2455631451],"iteration":335,"passed_time":15.65577295,"remaining_time":30.9387894},
{"learn":[0.2455547104],"iteration":336,"passed_time":15.6998346,"remaining_time":30.88721168},
{"learn":[0.2455497309],"iteration":337,"passed_time":15.74462754,"remaining_time":30.83711074},
{"learn":[0.2455415673],"iteration":338,"passed_time":15.79312623,"remaining_time":30.79426679},
{"learn":[0.2455278821],"iteration":339,"passed_time":15.83925981,"remaining_time":30.74679846},
{"learn":[0.2455048307],"iteration":340,"passed_time":15.88428432,"remaining_time":30.69719463},
{"learn":[0.2454979712],"iteration":341,"passed_time":15.93507363,"remaining_time":30.65870892},
{"learn":[0.2454890792],"iteration":342,"passed_time":15.98324185,"remaining_time":30.61513089},
{"learn":[0.2454784428],"iteration":343,"passed_time":16.02880501,"remaining_time":30.56655838},
{"learn":[0.2454685515],"iteration":344,"passed_time":16.07484113,"remaining_time":30.51890127},
{"learn":[0.245455239],"iteration":345,"passed_time":16.12772481,"remaining_time":30.4841966},
{"learn":[0.2454420111],"iteration":346,"passed_time":16.17397546,"remaining_time":30.43690483},
{"learn":[0.2454368283],"iteration":347,"passed_time":16.21756016,"remaining_time":30.3846242},
{"learn":[0.2454305616],"iteration":348,"passed_time":16.26628601,"remaining_time":30.34198336},
{"learn":[0.2454225334],"iteration":349,"passed_time":16.318692,"remaining_time":30.30614229},
{"learn":[0.2454050205],"iteration":350,"passed_time":16.36538792,"remaining_time":30.25964889},
{"learn":[0.2453937065],"iteration":351,"passed_time":16.41796269,"remaining_time":30.22397676},
{"learn":[0.2453862881],"iteration":352,"passed_time":16.46352167,"remaining_time":30.17534991},
{"learn":[0.2453678944],"iteration":353,"passed_time":16.50996458,"remaining_time":30.12835344},
{"learn":[0.2453521599],"iteration":354,"passed_time":16.55491941,"remaining_time":30.07865639},
{"learn":[0.2453409306],"iteration":355,"passed_time":16.6039578,"remaining_time":30.0363731},
{"learn":[0.245336239],"iteration":356,"passed_time":16.64657241,"remaining_time":29.98248196},
{"learn":[0.2453228079],"iteration":357,"passed_time":16.69227055,"remaining_time":29.93418349},
{"learn":[0.2453073613],"iteration":358,"passed_time":16.7402378,"remaining_time":29.88995106},
{"learn":[0.2452929478],"iteration":359,"passed_time":16.7880922,"remaining_time":29.84549724},
{"learn":[0.2452811766],"iteration":360,"passed_time":16.8369545,"remaining_time":29.80280866},
{"learn":[0.2452709127],"iteration":361,"passed_time":16.88279261,"remaining_time":29.75475603},
{"learn":[0.2452518754],"iteration":362,"passed_time":16.92878521,"remaining_time":29.70698672},
{"learn":[0.2452363102],"iteration":363,"passed_time":16.97413966,"remaining_time":29.65811215},
{"learn":[0.245226148],"iteration":364,"passed_time":17.02682742,"remaining_time":29.62201482},
{"learn":[0.2452180182],"iteration":365,"passed_time":17.07827963,"remaining_time":29.58368657},
{"learn":[0.2452061284],"iteration":366,"passed_time":17.12308345,"remaining_time":29.53381968},
{"learn":[0.245195729],"iteration":367,"passed_time":17.16428556,"remaining_time":29.47779477},
{"learn":[0.2451827721],"iteration":368,"passed_time":17.2112641,"remaining_time":29.43172805},
{"learn":[0.2451779959],"iteration":369,"passed_time":17.26109112,"remaining_time":29.3905065},
{"learn":[0.2451691547],"iteration":370,"passed_time":17.3102557,"remaining_time":29.34811546},
{"learn":[0.2451566043],"iteration":371,"passed_time":17.35714218,"remaining_time":29.30184217},
{"learn":[0.2451437491],"iteration":372,"passed_time":17.40323091,"remaining_time":29.25422462},
{"learn":[0.24513838],"iteration":373,"passed_time":17.44570684,"remaining_time":29.20056813},
{"learn":[0.2451249489],"iteration":374,"passed_time":17.49397765,"remaining_time":29.15662942},
{"learn":[0.2451115009],"iteration":375,"passed_time":17.54034169,"remaining_time":29.10950323},
{"learn":[0.2451011184],"iteration":376,"passed_time":17.58625817,"remaining_time":29.06164149},
{"learn":[0.2450833345],"iteration":377,"passed_time":17.63763738,"remaining_time":29.02277897},
{"learn":[0.2450716479],"iteration":378,"passed_time":17.68578885,"remaining_time":28.97856167},
{"learn":[0.2450600799],"iteration":379,"passed_time":17.7312402,"remaining_time":28.92991823},
{"learn":[0.2450465641],"iteration":380,"passed_time":17.77726942,"remaining_time":28.88223036},
{"learn":[0.2450395352],"iteration":381,"passed_time":17.82610764,"remaining_time":28.83909561},
{"learn":[0.2450283737],"iteration":382,"passed_time":17.87287801,"remaining_time":28.79259983},
{"learn":[0.2450192107],"iteration":383,"passed_time":17.91845573,"remaining_time":28.7441894},
{"learn":[0.2450114197],"iteration":384,"passed_time":17.96463148,"remaining_time":28.69674899},
{"learn":[0.2450054409],"iteration":385,"passed_time":18.0099214,"remaining_time":28.64790606},
{"learn":[0.2449906887],"iteration":386,"passed_time":18.05642707,"remaining_time":28.60100722},
{"learn":[0.2449807297],"iteration":387,"passed_time":18.10289076,"remaining_time":28.55404419},
{"learn":[0.2449723797],"iteration":388,"passed_time":18.15614747,"remaining_time":28.51775348},
{"learn":[0.244965029],"iteration":389,"passed_time":18.2128547,"remaining_time":28.48677274},
{"learn":[0.2449585252],"iteration":390,"passed_time":18.25434628,"remaining_time":28.43196134},
{"learn":[0.2449471942],"iteration":391,"passed_time":18.2997574,"remaining_time":28.38329719},
{"learn":[0.2449391999],"iteration":392,"passed_time":18.3464858,"remaining_time":28.33668417},
{"learn":[0.2449337293],"iteration":393,"passed_time":18.39502105,"remaining_time":28.29284964},
{"learn":[0.2449248881],"iteration":394,"passed_time":18.44404716,"remaining_time":28.24974312},
{"learn":[0.2449097802],"iteration":395,"passed_time":18.49311824,"remaining_time":28.20667529},
{"learn":[0.2448994825],"iteration":396,"passed_time":18.53996039,"remaining_time":28.16019173},
{"learn":[0.2448945707],"iteration":397,"passed_time":18.58953049,"remaining_time":28.11783255},
{"learn":[0.2448848319],"iteration":398,"passed_time":18.63736146,"remaining_time":28.07281763},
{"learn":[0.2448746697],"iteration":399,"passed_time":18.68263126,"remaining_time":28.02394689},
{"learn":[0.2448570551],"iteration":400,"passed_time":18.72664118,"remaining_time":27.97321214},
{"learn":[0.2448477058],"iteration":401,"passed_time":18.7744144,"remaining_time":27.92810899},
{"learn":[0.2448367475],"iteration":402,"passed_time":18.81954426,"remaining_time":27.87907673},
{"learn":[0.2448262635],"iteration":403,"passed_time":18.86553087,"remaining_time":27.83132771},
{"learn":[0.2448137131],"iteration":404,"passed_time":18.91137787,"remaining_time":27.7833823},
{"learn":[0.2448073109],"iteration":405,"passed_time":18.95632436,"remaining_time":27.73412973},
{"learn":[0.2448013321],"iteration":406,"passed_time":19.0035798,"remaining_time":27.68826246},
{"learn":[0.2447943032],"iteration":407,"passed_time":19.05685499,"remaining_time":27.65112292},
{"learn":[0.2447843611],"iteration":408,"passed_time":19.10224954,"remaining_time":27.60251706},
{"learn":[0.2447797034],"iteration":409,"passed_time":19.16419132,"remaining_time":27.57773872},
{"learn":[0.2447718785],"iteration":410,"passed_time":19.24670284,"remaining_time":27.58225783},
{"learn":[0.2447662723],"iteration":411,"passed_time":19.30403904,"remaining_time":27.55042464},
{"learn":[0.2447559068],"iteration":412,"passed_time":19.35725153,"remaining_time":27.5126069},
{"learn":[0.2447442711],"iteration":413,"passed_time":19.40488779,"remaining_time":27.46682185},
{"learn":[0.244732178],"iteration":414,"passed_time":19.45656819,"remaining_time":27.42672866},
{"learn":[0.2447211011],"iteration":415,"passed_time":19.50525211,"remaining_time":27.38237315},
{"learn":[0.2447085677],"iteration":416,"passed_time":19.55566811,"remaining_time":27.34041848},
{"learn":[0.2447007597],"iteration":417,"passed_time":19.60484337,"remaining_time":27.2966958},
{"learn":[0.2446955261],"iteration":418,"passed_time":19.65093929,"remaining_time":27.24867716},
{"learn":[0.2446865326],"iteration":419,"passed_time":19.69836346,"remaining_time":27.20250192},
{"learn":[0.2446781656],"iteration":420,"passed_time":19.75226259,"remaining_time":27.16522575},
{"learn":[0.2446667162],"iteration":421,"passed_time":19.79934676,"remaining_time":27.11853656},
{"learn":[0.2446592639],"iteration":422,"passed_time":19.84676698,"remaining_time":27.07230389},
{"learn":[0.2446474926],"iteration":423,"passed_time":19.89259985,"remaining_time":27.02390923},
{"learn":[0.2446239162],"iteration":424,"passed_time":19.94094258,"remaining_time":26.97892232},
{"learn":[0.2446198513],"iteration":425,"passed_time":19.98566368,"remaining_time":26.9290398},
{"learn":[0.2446084357],"iteration":426,"passed_time":20.0329673,"remaining_time":26.88264699},
{"learn":[0.2446038118],"iteration":427,"passed_time":20.08386939,"remaining_time":26.84105909},
{"learn":[0.2445967321],"iteration":428,"passed_time":20.1294043,"remaining_time":26.79228405},
{"learn":[0.2445842495],"iteration":429,"passed_time":20.17572384,"remaining_time":26.74456417},
{"learn":[0.2445629088],"iteration":430,"passed_time":20.22445599,"remaining_time":26.70003587},
{"learn":[0.2445553887],"iteration":431,"passed_time":20.27090763,"remaining_time":26.65248966},
{"learn":[0.2445482582],"iteration":432,"passed_time":20.31944465,"remaining_time":26.60767925},
{"learn":[0.2445442272],"iteration":433,"passed_time":20.37258198,"remaining_time":26.56885115},
{"learn":[0.2445331842],"iteration":434,"passed_time":20.41835367,"remaining_time":26.5203904},
{"learn":[0.2445213283],"iteration":435,"passed_time":20.4642685,"remaining_time":26.47212714},
{"learn":[0.244514672],"iteration":436,"passed_time":20.50991047,"remaining_time":26.42352309},
{"learn":[0.2445082698],"iteration":437,"passed_time":20.55997227,"remaining_time":26.38060368},
{"learn":[0.244497718],"iteration":438,"passed_time":20.61055398,"remaining_time":26.33831614},
{"learn":[0.2444789178],"iteration":439,"passed_time":20.65736502,"remaining_time":26.29119185},
{"learn":[0.2444698565],"iteration":440,"passed_time":20.70635019,"remaining_time":26.24682484},
{"learn":[0.2444652665],"iteration":441,"passed_time":20.75428257,"remaining_time":26.20110786},
{"learn":[0.2444567641],"iteration":442,"passed_time":20.80162313,"remaining_time":26.15463676},
{"learn":[0.2444520725],"iteration":443,"passed_time":20.84862122,"remaining_time":26.10773288},
{"learn":[0.2444480584],"iteration":444,"passed_time":20.89188728,"remaining_time":26.05617402},
{"learn":[0.2444406739],"iteration":445,"passed_time":20.94186174,"remaining_time":26.01298521},
{"learn":[0.2444354234],"iteration":446,"passed_time":20.99639891,"remaining_time":25.97541073},
{"learn":[0.2444295123],"iteration":447,"passed_time":21.04996478,"remaining_time":25.93656374},
{"learn":[0.2444106444],"iteration":448,"passed_time":21.0959266,"remaining_time":25.88831973},
{"learn":[0.2443967899],"iteration":449,"passed_time":21.14189502,"remaining_time":25.84009391},
{"learn":[0.2443907603],"iteration":450,"passed_time":21.18907176,"remaining_time":25.793349},
{"learn":[0.2443776171],"iteration":451,"passed_time":21.23195559,"remaining_time":25.74139749},
{"learn":[0.2443642876],"iteration":452,"passed_time":21.2792851,"remaining_time":25.69485419},
{"learn":[0.2443539391],"iteration":453,"passed_time":21.32572031,"remaining_time":25.64723192},
{"learn":[0.2443445051],"iteration":454,"passed_time":21.37520988,"remaining_time":25.60327337},
{"learn":[0.2443423541],"iteration":455,"passed_time":21.41628941,"remaining_time":25.54925754},
{"learn":[0.2443257896],"iteration":456,"passed_time":21.46259602,"remaining_time":25.50150906},
{"learn":[0.2443207424],"iteration":457,"passed_time":21.50677735,"remaining_time":25.4512518},
{"learn":[0.2443155088],"iteration":458,"passed_time":21.55155075,"remaining_time":25.40171886},
{"learn":[0.2443097333],"iteration":459,"passed_time":21.60095034,"remaining_time":25.35763735},
{"learn":[0.2443028907],"iteration":460,"passed_time":21.64562701,"remaining_time":25.30801076},
{"learn":[0.2442885789],"iteration":461,"passed_time":21.6918092,"remaining_time":25.26015877},
{"learn":[0.2442807201],"iteration":462,"passed_time":21.74083285,"remaining_time":25.21560959},
{"learn":[0.2442773327],"iteration":463,"passed_time":21.78576273,"remaining_time":25.16631212},
{"learn":[0.2442715571],"iteration":464,"passed_time":21.83613148,"remaining_time":25.12329105},
{"learn":[0.2442625974],"iteration":465,"passed_time":21.88491258,"remaining_time":25.07841913},
{"learn":[0.2442564662],"iteration":466,"passed_time":21.93171693,"remaining_time":25.03127435},
{"learn":[0.2442437464],"iteration":467,"passed_time":21.97710759,"remaining_time":24.98252401},
{"learn":[0.2442169689],"iteration":468,"passed_time":22.023394,"remaining_time":24.93480216},
{"learn":[0.2442083987],"iteration":469,"passed_time":22.07330129,"remaining_time":24.89116954},
{"learn":[0.2441878371],"iteration":470,"passed_time":22.11748871,"remaining_time":24.84108604},
{"learn":[0.2441768111],"iteration":471,"passed_time":22.16272253,"remaining_time":24.79219809},
{"learn":[0.2441711372],"iteration":472,"passed_time":22.21111152,"remaining_time":24.74684096},
{"learn":[0.2441608902],"iteration":473,"passed_time":22.25552818,"remaining_time":24.69706292},
{"learn":[0.2441513716],"iteration":474,"passed_time":22.30025588,"remaining_time":24.64765124},
{"learn":[0.2441299292],"iteration":475,"passed_time":22.34770357,"remaining_time":24.60125351},
{"learn":[0.2441183781],"iteration":476,"passed_time":22.39496613,"remaining_time":24.5546484},
{"learn":[0.2441105193],"iteration":477,"passed_time":22.44333194,"remaining_time":24.50924534},
{"learn":[0.2441077078],"iteration":478,"passed_time":22.4879988,"remaining_time":24.45980663},
{"learn":[0.2440982908],"iteration":479,"passed_time":22.5341262,"remaining_time":24.41197005},
{"learn":[0.2440918208],"iteration":480,"passed_time":22.58002336,"remaining_time":24.36389215},
{"learn":[0.2440779832],"iteration":481,"passed_time":22.62633781,"remaining_time":24.31627175},
{"learn":[0.2440636375],"iteration":482,"passed_time":22.67188787,"remaining_time":24.26783857},
{"learn":[0.2440545762],"iteration":483,"passed_time":22.7207608,"remaining_time":24.22295986},
{"learn":[0.2440458874],"iteration":484,"passed_time":22.76982995,"remaining_time":24.17827304},
{"learn":[0.2440403829],"iteration":485,"passed_time":22.81513835,"remaining_time":24.12959077},
{"learn":[0.2440374528],"iteration":486,"passed_time":22.87166523,"remaining_time":24.09273976},
{"learn":[0.2440263082],"iteration":487,"passed_time":22.9181385,"remaining_time":24.04526006},
{"learn":[0.2440243773],"iteration":488,"passed_time":22.97134776,"remaining_time":24.00482353},
{"learn":[0.244015858],"iteration":489,"passed_time":23.01683076,"remaining_time":23.95629324},
{"learn":[0.2440083379],"iteration":490,"passed_time":23.06342555,"remaining_time":23.90892791},
{"learn":[0.2439959569],"iteration":491,"passed_time":23.10983228,"remaining_time":23.86137154},
{"learn":[0.2439754461],"iteration":492,"passed_time":23.15612807,"remaining_time":23.81370574},
{"learn":[0.2439688745],"iteration":493,"passed_time":23.20822541,"remaining_time":23.77198797},
{"learn":[0.2439479234],"iteration":494,"passed_time":23.25346955,"remaining_time":23.72323661},
{"learn":[0.2439326969],"iteration":495,"passed_time":23.29855282,"remaining_time":23.67433593},
{"learn":[0.2439214338],"iteration":496,"passed_time":23.34537833,"remaining_time":23.62721388},
{"learn":[0.2439117796],"iteration":497,"passed_time":23.38926434,"remaining_time":23.57712992},
{"learn":[0.2438992123],"iteration":498,"passed_time":23.43585157,"remaining_time":23.52978284},
{"learn":[0.2438865434],"iteration":499,"passed_time":23.48114582,"remaining_time":23.48114582},
{"learn":[0.2438732308],"iteration":500,"passed_time":23.52721424,"remaining_time":23.43329323},
{"learn":[0.2438520764],"iteration":501,"passed_time":23.57271065,"remaining_time":23.38488028},
{"learn":[0.243842236],"iteration":502,"passed_time":23.61805667,"remaining_time":23.33633034},
{"learn":[0.2438337674],"iteration":503,"passed_time":23.6633905,"remaining_time":23.28778113},
{"learn":[0.2438194725],"iteration":504,"passed_time":23.70907957,"remaining_time":23.23959285},
{"learn":[0.2438034331],"iteration":505,"passed_time":23.75422835,"remaining_time":23.19088696},
{"learn":[0.2438010111],"iteration":506,"passed_time":23.80313433,"remaining_time":23.14584857},
{"learn":[0.2437952186],"iteration":507,"passed_time":23.84940452,"remaining_time":23.09824218},
{"learn":[0.2437903407],"iteration":508,"passed_time":23.89875419,"remaining_time":23.05361161},
{"learn":[0.2437839724],"iteration":509,"passed_time":23.94707736,"remaining_time":23.00797629},
{"learn":[0.2437788405],"iteration":510,"passed_time":23.99413429,"remaining_time":22.96111873},
{"learn":[0.24376524],"iteration":511,"passed_time":24.04239117,"remaining_time":22.91540409},
{"learn":[0.2437564327],"iteration":512,"passed_time":24.08969577,"remaining_time":22.86877552},
{"learn":[0.2437456438],"iteration":513,"passed_time":24.1355844,"remaining_time":22.82080548},
{"learn":[0.2437387504],"iteration":514,"passed_time":24.18088778,"remaining_time":22.77229238},
{"learn":[0.2437276058],"iteration":515,"passed_time":24.22964206,"remaining_time":22.7270286},
{"learn":[0.2437126673],"iteration":516,"passed_time":24.27831377,"remaining_time":22.68167418},
{"learn":[0.2437037245],"iteration":517,"passed_time":24.32367812,"remaining_time":22.63322945},
{"learn":[0.2436938163],"iteration":518,"passed_time":24.37095456,"remaining_time":22.58656868},
{"learn":[0.243674237],"iteration":519,"passed_time":24.41712673,"remaining_time":22.53888622},
{"learn":[0.2436635328],"iteration":520,"passed_time":24.46321895,"remaining_time":22.49113604},
{"learn":[0.2436554708],"iteration":521,"passed_time":24.50984132,"remaining_time":22.44387768},
{"learn":[0.2436447665],"iteration":522,"passed_time":24.55538388,"remaining_time":22.39563692},
{"learn":[0.24363872],"iteration":523,"passed_time":24.60175533,"remaining_time":22.34815942},
{"learn":[0.2436281343],"iteration":524,"passed_time":24.64813603,"remaining_time":22.3006945},
{"learn":[0.2436240525],"iteration":525,"passed_time":24.6939829,"remaining_time":22.25275265},
{"learn":[0.2436082332],"iteration":526,"passed_time":24.73985314,"remaining_time":22.20483972},
{"learn":[0.2435998324],"iteration":527,"passed_time":24.78545243,"remaining_time":22.15669232},
{"learn":[0.2435963942],"iteration":528,"passed_time":24.82511831,"remaining_time":22.10327169},
{"learn":[0.2435819977],"iteration":529,"passed_time":24.87127623,"remaining_time":22.05566006},
{"learn":[0.2435726654],"iteration":530,"passed_time":24.91718889,"remaining_time":22.00783727},
{"learn":[0.2435558299],"iteration":531,"passed_time":24.96595201,"remaining_time":21.96252921},
{"learn":[0.2435481743],"iteration":532,"passed_time":25.01349334,"remaining_time":21.91613769},
{"learn":[0.2435445329],"iteration":533,"passed_time":25.055956,"remaining_time":21.86530992},
{"learn":[0.2435371483],"iteration":534,"passed_time":25.10172729,"remaining_time":21.81738914},
{"learn":[0.2435292556],"iteration":535,"passed_time":25.14625042,"remaining_time":21.76839589},
{"learn":[0.2435173827],"iteration":536,"passed_time":25.19274552,"remaining_time":21.72111951},
{"learn":[0.2435071866],"iteration":537,"passed_time":25.23834197,"remaining_time":21.67307434},
{"learn":[0.2434936369],"iteration":538,"passed_time":25.28564668,"remaining_time":21.62649929},
{"learn":[0.2434882848],"iteration":539,"passed_time":25.33318027,"remaining_time":21.58011653},
{"learn":[0.2434801042],"iteration":540,"passed_time":25.37857831,"remaining_time":21.53191765},
{"learn":[0.2434726688],"iteration":541,"passed_time":25.42429502,"remaining_time":21.48399837},
{"learn":[0.2434636583],"iteration":542,"passed_time":25.46962909,"remaining_time":21.43576519},
{"learn":[0.2434592208],"iteration":543,"passed_time":25.51508069,"remaining_time":21.38764117},
{"learn":[0.2434545631],"iteration":544,"passed_time":25.56075171,"remaining_time":21.33971014},
{"learn":[0.2434401158],"iteration":545,"passed_time":25.60657165,"remaining_time":21.29191123},
{"learn":[0.2434378462],"iteration":546,"passed_time":25.65233777,"remaining_time":21.24407497},
{"learn":[0.2434251603],"iteration":547,"passed_time":25.69829583,"remaining_time":21.19640459},
{"learn":[0.2434167595],"iteration":548,"passed_time":25.74406324,"remaining_time":21.14858383},
{"learn":[0.2434042261],"iteration":549,"passed_time":25.78915677,"remaining_time":21.10021918},
{"learn":[0.2433985691],"iteration":550,"passed_time":25.8342332,"remaining_time":21.05185247},
{"learn":[0.24339132],"iteration":551,"passed_time":25.87905191,"remaining_time":21.0032885},
{"learn":[0.2433887117],"iteration":552,"passed_time":25.92320527,"remaining_time":20.95420028},
{"learn":[0.2433797859],"iteration":553,"passed_time":25.96947816,"remaining_time":20.90683621},
{"learn":[0.243373282],"iteration":554,"passed_time":26.01555008,"remaining_time":20.85931493},
{"learn":[0.2433625101],"iteration":555,"passed_time":26.0647695,"remaining_time":20.81431233},
{"learn":[0.2433580556],"iteration":556,"passed_time":26.11157793,"remaining_time":20.76737706},
{"learn":[0.2433436252],"iteration":557,"passed_time":26.1574293,"remaining_time":20.71968414},
{"learn":[0.2433347671],"iteration":558,"passed_time":26.20422156,"remaining_time":20.67274009},
{"learn":[0.2433309563],"iteration":559,"passed_time":26.24899871,"remaining_time":20.62421327},
{"learn":[0.2433229112],"iteration":560,"passed_time":26.29391532,"remaining_time":20.57580896},
{"learn":[0.2433156621],"iteration":561,"passed_time":26.34036918,"remaining_time":20.52861513},
{"learn":[0.2433043142],"iteration":562,"passed_time":26.38629302,"remaining_time":20.48101252},
{"learn":[0.2432977765],"iteration":563,"passed_time":26.43176914,"remaining_time":20.43306976},
{"learn":[0.2432915606],"iteration":564,"passed_time":26.47515632,"remaining_time":20.38352743},
{"learn":[0.2432880885],"iteration":565,"passed_time":26.52364976,"remaining_time":20.33792225},
{"learn":[0.2432815677],"iteration":566,"passed_time":26.56826296,"remaining_time":20.28934367},
{"learn":[0.2432743525],"iteration":567,"passed_time":26.61590894,"remaining_time":20.24308567},
{"learn":[0.2432689666],"iteration":568,"passed_time":26.66613036,"remaining_time":20.19877362},
{"learn":[0.2432630386],"iteration":569,"passed_time":26.71552972,"remaining_time":20.15382067},
{"learn":[0.2432519617],"iteration":570,"passed_time":26.76447556,"remaining_time":20.10851141},
{"learn":[0.243239496],"iteration":571,"passed_time":26.81222773,"remaining_time":20.06229627},
{"learn":[0.2432295878],"iteration":572,"passed_time":26.85835526,"remaining_time":20.01486509},
{"learn":[0.2432165463],"iteration":573,"passed_time":26.90390595,"remaining_time":19.96701034},
{"learn":[0.2432078067],"iteration":574,"passed_time":26.94965321,"remaining_time":19.91930889},
{"learn":[0.2431988978],"iteration":575,"passed_time":26.99805093,"remaining_time":19.87356527},
{"learn":[0.2431952225],"iteration":576,"passed_time":27.04272635,"remaining_time":19.82508362},
{"learn":[0.2431824689],"iteration":577,"passed_time":27.08825934,"remaining_time":19.77724125},
{"learn":[0.2431772692],"iteration":578,"passed_time":27.13974112,"remaining_time":19.73373232},
{"learn":[0.2431610096],"iteration":579,"passed_time":27.18487254,"remaining_time":19.68559736},
{"learn":[0.2431463251],"iteration":580,"passed_time":27.23095413,"remaining_time":19.63815797},
{"learn":[0.2431409053],"iteration":581,"passed_time":27.27972674,"remaining_time":19.59265598},
{"learn":[0.2431352822],"iteration":582,"passed_time":27.32946665,"remaining_time":19.54783464},
{"learn":[0.2431245441],"iteration":583,"passed_time":27.37485279,"remaining_time":19.49989514},
{"learn":[0.2431185483],"iteration":584,"passed_time":27.42371309,"remaining_time":19.45442895},
{"learn":[0.2431089958],"iteration":585,"passed_time":27.47339607,"remaining_time":19.40953237},
{"learn":[0.2430994602],"iteration":586,"passed_time":27.52278573,"remaining_time":19.36441313},
{"learn":[0.2430880616],"iteration":587,"passed_time":27.56770836,"remaining_time":19.31614939},
{"learn":[0.2430724287],"iteration":588,"passed_time":27.61715788,"remaining_time":19.27105584},
{"learn":[0.2430581168],"iteration":589,"passed_time":27.66393203,"remaining_time":19.22408836},
{"learn":[0.2430514605],"iteration":590,"passed_time":27.71306461,"remaining_time":19.17875368},
{"learn":[0.2430429073],"iteration":591,"passed_time":27.75810431,"remaining_time":19.13058541},
{"learn":[0.2430363696],"iteration":592,"passed_time":27.81320056,"remaining_time":19.0893299},
{"learn":[0.2430298996],"iteration":593,"passed_time":27.85923001,"remaining_time":19.04183062},
{"learn":[0.2430197035],"iteration":594,"passed_time":27.9041971,"remaining_time":18.99361315},
{"learn":[0.2430092533],"iteration":595,"passed_time":27.94951793,"remaining_time":18.94564638},
{"learn":[0.2430032745],"iteration":596,"passed_time":27.99483154,"remaining_time":18.8976836},
{"learn":[0.2429985491],"iteration":597,"passed_time":28.04398276,"remaining_time":18.85230948},
{"learn":[0.242990233],"iteration":598,"passed_time":28.08867229,"remaining_time":18.80393588},
{"learn":[0.2429835767],"iteration":599,"passed_time":28.13606379,"remaining_time":18.75737586},
{"learn":[0.2429754469],"iteration":600,"passed_time":28.18172484,"remaining_time":18.70966424},
{"learn":[0.2429670123],"iteration":601,"passed_time":28.22717414,"remaining_time":18.66181945},
{"learn":[0.2429610504],"iteration":602,"passed_time":28.27961549,"remaining_time":18.61858599},
{"learn":[0.2429454514],"iteration":603,"passed_time":28.32665583,"remaining_time":18.57178098},
{"learn":[0.2429391677],"iteration":604,"passed_time":28.37444397,"remaining_time":18.52546342},
{"learn":[0.2429270069],"iteration":605,"passed_time":28.41993306,"remaining_time":18.47764625},
{"learn":[0.2429241784],"iteration":606,"passed_time":28.46426212,"remaining_time":18.42908569},
{"learn":[0.2429177931],"iteration":607,"passed_time":28.51092494,"remaining_time":18.38204371},
{"learn":[0.2429033119],"iteration":608,"passed_time":28.55874248,"remaining_time":18.33574435},
{"learn":[0.24289359],"iteration":609,"passed_time":28.60711365,"remaining_time":18.28979397},
{"learn":[0.242889542],"iteration":610,"passed_time":28.652616,"remaining_time":18.2420092},
{"learn":[0.2428810735],"iteration":611,"passed_time":28.70483642,"remaining_time":18.19849106},
{"learn":[0.2428588012],"iteration":612,"passed_time":28.75048184,"remaining_time":18.15079359},
{"learn":[0.242854025],"iteration":613,"passed_time":28.79437519,"remaining_time":18.10200134},
{"learn":[0.2428458105],"iteration":614,"passed_time":28.83933262,"remaining_time":18.05389116},
{"learn":[0.2428353434],"iteration":615,"passed_time":28.88777067,"remaining_time":18.00796094},
{"learn":[0.2428294832],"iteration":616,"passed_time":28.93414759,"remaining_time":17.96074316},
{"learn":[0.2428189991],"iteration":617,"passed_time":28.98220411,"remaining_time":17.91456629},
{"learn":[0.2428026887],"iteration":618,"passed_time":29.02782996,"remaining_time":17.86688726},
{"learn":[0.2427923232],"iteration":619,"passed_time":29.07633307,"remaining_time":17.82097833},
{"learn":[0.242783228],"iteration":620,"passed_time":29.12257211,"remaining_time":17.77367927},
{"learn":[0.2427785533],"iteration":621,"passed_time":29.17262149,"remaining_time":17.72869923},
{"learn":[0.242774607],"iteration":622,"passed_time":29.22141212,"remaining_time":17.6829412},
{"learn":[0.2427610065],"iteration":623,"passed_time":29.26749329,"remaining_time":17.63554083},
{"learn":[0.2427540285],"iteration":624,"passed_time":29.31581224,"remaining_time":17.58948734},
{"learn":[0.2427427992],"iteration":625,"passed_time":29.36317371,"remaining_time":17.54285458},
{"learn":[0.242736922],"iteration":626,"passed_time":29.40864546,"remaining_time":17.4950953},
{"learn":[0.2427191889],"iteration":627,"passed_time":29.45512515,"remaining_time":17.44794038},
{"learn":[0.2427101783],"iteration":628,"passed_time":29.50070375,"remaining_time":17.40025611},
{"learn":[0.2426928348],"iteration":629,"passed_time":29.54755672,"remaining_time":17.35332696},
{"learn":[0.2426807078],"iteration":630,"passed_time":29.59717864,"remaining_time":17.3080173},
{"learn":[0.2426751186],"iteration":631,"passed_time":29.64736423,"remaining_time":17.26302221},
{"learn":[0.2426707996],"iteration":632,"passed_time":29.69565169,"remaining_time":17.21691022},
{"learn":[0.242661552],"iteration":633,"passed_time":29.74279346,"remaining_time":17.17012998},
{"learn":[0.2426558273],"iteration":634,"passed_time":29.79161923,"remaining_time":17.12431656},
{"learn":[0.2426450553],"iteration":635,"passed_time":29.83789874,"remaining_time":17.07703639},
{"learn":[0.2426398048],"iteration":636,"passed_time":29.88189887,"remaining_time":17.02846042},
{"learn":[0.242631387],"iteration":637,"passed_time":29.92746205,"remaining_time":16.98078568},
{"learn":[0.2426181592],"iteration":638,"passed_time":29.97308143,"remaining_time":16.93314929},
{"learn":[0.2426077598],"iteration":639,"passed_time":30.01790632,"remaining_time":16.8850723},
{"learn":[0.2425968523],"iteration":640,"passed_time":30.06394297,"remaining_time":16.83768413},
{"learn":[0.2425888919],"iteration":641,"passed_time":30.11008975,"remaining_time":16.79036157},
{"learn":[0.2425774932],"iteration":642,"passed_time":30.15512702,"remaining_time":16.74242666},
{"learn":[0.2425742413],"iteration":643,"passed_time":30.20219336,"remaining_time":16.69562242},
{"learn":[0.2425671955],"iteration":644,"passed_time":30.24645548,"remaining_time":16.64727394},
{"learn":[0.2425605731],"iteration":645,"passed_time":30.29046729,"remaining_time":16.59880096},
{"learn":[0.2425548653],"iteration":646,"passed_time":30.3418677,"remaining_time":16.55437295},
{"learn":[0.2425385041],"iteration":647,"passed_time":30.38762212,"remaining_time":16.50685646},
{"learn":[0.2425271224],"iteration":648,"passed_time":30.43357774,"remaining_time":16.45945422},
{"learn":[0.242523176],"iteration":649,"passed_time":30.47732016,"remaining_time":16.4108647},
{"learn":[0.2425097957],"iteration":650,"passed_time":30.52228727,"remaining_time":16.36294663},
{"learn":[0.242494112],"iteration":651,"passed_time":30.56732258,"remaining_time":16.31507401},
{"learn":[0.2424784283],"iteration":652,"passed_time":30.61273801,"remaining_time":16.26741208},
{"learn":[0.2424672159],"iteration":653,"passed_time":30.66152548,"remaining_time":16.221541},
{"learn":[0.2424572061],"iteration":654,"passed_time":30.70624619,"remaining_time":16.17351898},
{"learn":[0.2424431653],"iteration":655,"passed_time":30.75062408,"remaining_time":16.12532726},
{"learn":[0.242434341],"iteration":656,"passed_time":30.79537652,"remaining_time":16.07734269},
{"learn":[0.242429785],"iteration":657,"passed_time":30.83936487,"remaining_time":16.0289708},
{"learn":[0.2424221802],"iteration":658,"passed_time":30.88495776,"remaining_time":15.98144248},
{"learn":[0.242416862],"iteration":659,"passed_time":30.93276592,"remaining_time":15.93506123},
{"learn":[0.2424079022],"iteration":660,"passed_time":30.982015,"remaining_time":15.88941465},
{"learn":[0.242398807],"iteration":661,"passed_time":31.02768414,"remaining_time":15.84192937},
{"learn":[0.2423920491],"iteration":662,"passed_time":31.07219357,"remaining_time":15.79386008},
{"learn":[0.2423818869],"iteration":663,"passed_time":31.11653955,"remaining_time":15.74571881},
{"learn":[0.2423755524],"iteration":664,"passed_time":31.16413206,"remaining_time":15.69922442},
{"learn":[0.2423692857],"iteration":665,"passed_time":31.20760016,"remaining_time":15.65065834},
{"learn":[0.2423618164],"iteration":666,"passed_time":31.25314533,"remaining_time":15.60314452},
{"learn":[0.2423571249],"iteration":667,"passed_time":31.30082038,"remaining_time":15.55669516},
{"learn":[0.2423507396],"iteration":668,"passed_time":31.34900533,"remaining_time":15.51049441},
{"learn":[0.2423464545],"iteration":669,"passed_time":31.39642826,"remaining_time":15.46391243},
{"learn":[0.2423396119],"iteration":670,"passed_time":31.43972579,"remaining_time":15.41530519},
{"learn":[0.2423331928],"iteration":671,"passed_time":31.48404556,"remaining_time":15.36721271},
{"learn":[0.2423196431],"iteration":672,"passed_time":31.52978121,"remaining_time":15.3198194},
{"learn":[0.2423139184],"iteration":673,"passed_time":31.57686784,"remaining_time":15.27308445},
{"learn":[0.2423095994],"iteration":674,"passed_time":31.62198878,"remaining_time":15.225402},
{"learn":[0.242302164],"iteration":675,"passed_time":31.67117785,"remaining_time":15.17967696},
{"learn":[0.2422937802],"iteration":676,"passed_time":31.71579358,"remaining_time":15.13175971},
{"learn":[0.242292476],"iteration":677,"passed_time":31.76657843,"remaining_time":15.08678209},
{"learn":[0.2422806709],"iteration":678,"passed_time":31.81140368,"remaining_time":15.03896993},
{"learn":[0.2422745735],"iteration":679,"passed_time":31.85679632,"remaining_time":14.99143356},
{"learn":[0.2422716942],"iteration":680,"passed_time":31.90109627,"remaining_time":14.94339164},
{"learn":[0.242259906],"iteration":681,"passed_time":31.94621844,"remaining_time":14.89574408},
{"learn":[0.2422500148],"iteration":682,"passed_time":31.99356144,"remaining_time":14.84913466},
{"learn":[0.2422425625],"iteration":683,"passed_time":32.04001843,"remaining_time":14.80211378},
{"learn":[0.2422408687],"iteration":684,"passed_time":32.08739852,"remaining_time":14.75551903},
{"learn":[0.2422315872],"iteration":685,"passed_time":32.13380907,"remaining_time":14.7084782},
{"learn":[0.242226811],"iteration":686,"passed_time":32.17890979,"remaining_time":14.66084245},
{"learn":[0.242218986],"iteration":687,"passed_time":32.22483256,"remaining_time":14.61358686},
{"learn":[0.2422116523],"iteration":688,"passed_time":32.26955042,"remaining_time":14.56579126},
{"learn":[0.2422086205],"iteration":689,"passed_time":32.31832233,"remaining_time":14.51982597},
{"learn":[0.2421938683],"iteration":690,"passed_time":32.36366001,"remaining_time":14.47231685},
{"learn":[0.2421870766],"iteration":691,"passed_time":32.40755096,"remaining_time":14.42417008},
{"learn":[0.2421826391],"iteration":692,"passed_time":32.45482531,"remaining_time":14.37753444},
{"learn":[0.2421773378],"iteration":693,"passed_time":32.49934865,"remaining_time":14.32968399},
{"learn":[0.2421671755],"iteration":694,"passed_time":32.54401076,"remaining_time":14.281904},
{"learn":[0.2421560309],"iteration":695,"passed_time":32.5896755,"remaining_time":14.23457091},
{"learn":[0.2421525927],"iteration":696,"passed_time":32.63463162,"remaining_time":14.18693455},
{"learn":[0.2421483584],"iteration":697,"passed_time":32.67895897,"remaining_time":14.13903383},
{"learn":[0.2421451573],"iteration":698,"passed_time":32.72428907,"remaining_time":14.09157512},
{"learn":[0.2421326408],"iteration":699,"passed_time":32.77165829,"remaining_time":14.04499641},
{"learn":[0.2421216825],"iteration":700,"passed_time":32.81609956,"remaining_time":13.99716657},
{"learn":[0.2421110968],"iteration":701,"passed_time":32.86084399,"remaining_time":13.94947508},
{"learn":[0.2421035768],"iteration":702,"passed_time":32.90600203,"remaining_time":13.90196672},
{"learn":[0.242094346],"iteration":703,"passed_time":32.95680888,"remaining_time":13.8568401},
{"learn":[0.2420844209],"iteration":704,"passed_time":33.00098914,"remaining_time":13.80892453},
{"learn":[0.2420774767],"iteration":705,"passed_time":33.04483423,"remaining_time":13.76087998},
{"learn":[0.2420739707],"iteration":706,"passed_time":33.09277341,"remaining_time":13.714544},
{"learn":[0.2420651804],"iteration":707,"passed_time":33.13857493,"remaining_time":13.66732186},
{"learn":[0.2420610647],"iteration":708,"passed_time":33.18724186,"remaining_time":13.6212798},
{"learn":[0.2420522405],"iteration":709,"passed_time":33.23053874,"remaining_time":13.57303695},
{"learn":[0.2420485143],"iteration":710,"passed_time":33.27786285,"remaining_time":13.52644496},
{"learn":[0.2420462617],"iteration":711,"passed_time":33.32708396,"remaining_time":13.48061823},
{"learn":[0.2420396223],"iteration":712,"passed_time":33.37219033,"remaining_time":13.4331257},
{"learn":[0.2420323055],"iteration":713,"passed_time":33.41728542,"remaining_time":13.38563533},
{"learn":[0.2420236337],"iteration":714,"passed_time":33.46408851,"remaining_time":13.33883248},
{"learn":[0.2420107107],"iteration":715,"passed_time":33.50822887,"remaining_time":13.29097346},
{"learn":[0.2420013615],"iteration":716,"passed_time":33.55394808,"remaining_time":13.24374799},
{"learn":[0.2419967715],"iteration":717,"passed_time":33.59839462,"remaining_time":13.19602686},
{"learn":[0.2419868803],"iteration":718,"passed_time":33.64284085,"remaining_time":13.14831471},
{"learn":[0.2419782254],"iteration":719,"passed_time":33.68760713,"remaining_time":13.10073611},
{"learn":[0.2419725007],"iteration":720,"passed_time":33.73454883,"remaining_time":13.0540071},
{"learn":[0.2419610851],"iteration":721,"passed_time":33.77838789,"remaining_time":13.00608287},
{"learn":[0.2419545304],"iteration":722,"passed_time":33.82469174,"remaining_time":12.95911426},
{"learn":[0.2419397613],"iteration":723,"passed_time":33.86932095,"remaining_time":12.91150909},
{"learn":[0.2419308693],"iteration":724,"passed_time":33.91370674,"remaining_time":12.8638198},
{"learn":[0.2419251277],"iteration":725,"passed_time":33.96211951,"remaining_time":12.81765943},
{"learn":[0.2419158631],"iteration":726,"passed_time":34.01154062,"remaining_time":12.77187151},
{"learn":[0.2419047185],"iteration":727,"passed_time":34.05685291,"remaining_time":12.72453845},
{"learn":[0.2419022118],"iteration":728,"passed_time":34.10809823,"remaining_time":12.67941649},
{"learn":[0.2418937602],"iteration":729,"passed_time":34.15278536,"remaining_time":12.63185212},
{"learn":[0.2418906946],"iteration":730,"passed_time":34.19750126,"remaining_time":12.58430621},
{"learn":[0.2418853425],"iteration":731,"passed_time":34.24277841,"remaining_time":12.53697352},
{"learn":[0.2418797363],"iteration":732,"passed_time":34.2893279,"remaining_time":12.49010989},
{"learn":[0.241874164],"iteration":733,"passed_time":34.33500273,"remaining_time":12.44293014},
{"learn":[0.2418639848],"iteration":734,"passed_time":34.38023255,"remaining_time":12.39559405},
{"learn":[0.2418561599],"iteration":735,"passed_time":34.42527528,"remaining_time":12.34819657},
{"learn":[0.2418474711],"iteration":736,"passed_time":34.46968705,"remaining_time":12.30058032},
{"learn":[0.2418416956],"iteration":737,"passed_time":34.51451598,"remaining_time":12.25312085},
{"learn":[0.2418341247],"iteration":738,"passed_time":34.55907297,"remaining_time":12.20557245},
{"learn":[0.2418307034],"iteration":739,"passed_time":34.60345334,"remaining_time":12.15797009},
{"learn":[0.2418231834],"iteration":740,"passed_time":34.6489453,"remaining_time":12.11076496},
{"learn":[0.2418177127],"iteration":741,"passed_time":34.69378775,"remaining_time":12.0633386},
{"learn":[0.241812242],"iteration":742,"passed_time":34.74120286,"remaining_time":12.01680906},
{"learn":[0.2418080247],"iteration":743,"passed_time":34.78635937,"remaining_time":11.9695},
{"learn":[0.24179395],"iteration":744,"passed_time":34.83132582,"remaining_time":11.92213166},
{"learn":[0.2417832965],"iteration":745,"passed_time":34.87584281,"remaining_time":11.87461672},
{"learn":[0.2417725923],"iteration":746,"passed_time":34.92095815,"remaining_time":11.82731246},
{"learn":[0.2417686798],"iteration":747,"passed_time":34.95840769,"remaining_time":11.77743147},
{"learn":[0.2417638697],"iteration":748,"passed_time":35.00280829,"remaining_time":11.72991306},
{"learn":[0.2417581111],"iteration":749,"passed_time":35.04809541,"remaining_time":11.68269847},
{"learn":[0.241755164],"iteration":750,"passed_time":35.09286557,"remaining_time":11.63531761},
{"learn":[0.2417461027],"iteration":751,"passed_time":35.13698544,"remaining_time":11.58772924},
{"learn":[0.2417391754],"iteration":752,"passed_time":35.18214883,"remaining_time":11.54049238},
{"learn":[0.2417362115],"iteration":753,"passed_time":35.23322658,"remaining_time":11.49519064},
{"learn":[0.2417275566],"iteration":754,"passed_time":35.27966892,"remaining_time":11.44836938},
{"learn":[0.2417172589],"iteration":755,"passed_time":35.32772212,"remaining_time":11.40206905},
{"learn":[0.2417090274],"iteration":756,"passed_time":35.37202757,"remaining_time":11.35456103},
{"learn":[0.2417021171],"iteration":757,"passed_time":35.4212375,"remaining_time":11.30862728},
{"learn":[0.2416930558],"iteration":758,"passed_time":35.46629893,"remaining_time":11.26136765},
{"learn":[0.2416872464],"iteration":759,"passed_time":35.51494235,"remaining_time":11.21524495},
{"learn":[0.2416793537],"iteration":760,"passed_time":35.56209913,"remaining_time":11.16864874},
{"learn":[0.2416719183],"iteration":761,"passed_time":35.61032479,"remaining_time":11.12238491},
{"learn":[0.241666617],"iteration":762,"passed_time":35.65706704,"remaining_time":11.07565516},
{"learn":[0.2416603164],"iteration":763,"passed_time":35.70327378,"remaining_time":11.02875996},
{"learn":[0.24165073],"iteration":764,"passed_time":35.74648742,"remaining_time":10.98094712},
{"learn":[0.2416456658],"iteration":765,"passed_time":35.78838811,"remaining_time":10.93274519},
{"learn":[0.2416408049],"iteration":766,"passed_time":35.83635699,"remaining_time":10.8864031},
{"learn":[0.2416336574],"iteration":767,"passed_time":35.88439524,"remaining_time":10.84007773},
{"learn":[0.2416188375],"iteration":768,"passed_time":35.92939521,"remaining_time":10.79283523},
{"learn":[0.2416112835],"iteration":769,"passed_time":35.97668226,"remaining_time":10.74628171},
{"learn":[0.2416085397],"iteration":770,"passed_time":36.02275256,"remaining_time":10.6993649},
{"learn":[0.2416028658],"iteration":771,"passed_time":36.06936567,"remaining_time":10.65261059},
{"learn":[0.2415943634],"iteration":772,"passed_time":36.11476498,"remaining_time":10.6055002},
{"learn":[0.2415862844],"iteration":773,"passed_time":36.15986342,"remaining_time":10.55830637},
{"learn":[0.2415751567],"iteration":774,"passed_time":36.20836356,"remaining_time":10.51210555},
{"learn":[0.2415648251],"iteration":775,"passed_time":36.25347205,"remaining_time":10.46491977},
{"learn":[0.2415483792],"iteration":776,"passed_time":36.3003603,"remaining_time":10.41825012},
{"learn":[0.2415455846],"iteration":777,"passed_time":36.34822101,"remaining_time":10.37185741},
{"learn":[0.2415426714],"iteration":778,"passed_time":36.39056352,"remaining_time":10.32389543},
{"learn":[0.241529054],"iteration":779,"passed_time":36.4376916,"remaining_time":10.27729763},
{"learn":[0.2415212968],"iteration":780,"passed_time":36.48116414,"remaining_time":10.22967343},
{"learn":[0.2415135904],"iteration":781,"passed_time":36.52659377,"remaining_time":10.18260543},
{"learn":[0.2415095594],"iteration":782,"passed_time":36.57528191,"remaining_time":10.13644467},
{"learn":[0.2415038008],"iteration":783,"passed_time":36.62281702,"remaining_time":10.08995979},
{"learn":[0.2414943499],"iteration":784,"passed_time":36.6672019,"remaining_time":10.04260944},
{"learn":[0.2414877445],"iteration":785,"passed_time":36.71223915,"remaining_time":9.995444247},
{"learn":[0.2414863726],"iteration":786,"passed_time":36.75885397,"remaining_time":9.948711431},
{"learn":[0.2414781919],"iteration":787,"passed_time":36.80231691,"remaining_time":9.901130944},
{"learn":[0.2414734157],"iteration":788,"passed_time":36.84528241,"remaining_time":9.853427869},
{"learn":[0.2414687919],"iteration":789,"passed_time":36.88912906,"remaining_time":9.805971017},
{"learn":[0.2414557673],"iteration":790,"passed_time":36.93357738,"remaining_time":9.758682266},
{"learn":[0.2414480439],"iteration":791,"passed_time":36.97865597,"remaining_time":9.711566215},
{"learn":[0.2414441315],"iteration":792,"passed_time":37.02353766,"remaining_time":9.664403904},
{"learn":[0.2414347653],"iteration":793,"passed_time":37.06721059,"remaining_time":9.616933731},
{"learn":[0.2414287695],"iteration":794,"passed_time":37.11141949,"remaining_time":9.569611315},
{"learn":[0.2414214866],"iteration":795,"passed_time":37.15569187,"remaining_time":9.522312993},
{"learn":[0.2414198268],"iteration":796,"passed_time":37.23104812,"remaining_time":9.482939484},
{"learn":[0.2414139157],"iteration":797,"passed_time":37.31746954,"remaining_time":9.446276751},
{"learn":[0.2414052947],"iteration":798,"passed_time":37.363914,"remaining_time":9.399432683},
{"learn":[0.2414015178],"iteration":799,"passed_time":37.41212361,"remaining_time":9.353030903},
{"learn":[0.2413930323],"iteration":800,"passed_time":37.4568271,"remaining_time":9.30575355},
{"learn":[0.2413863083],"iteration":801,"passed_time":37.50180064,"remaining_time":9.258549285},
{"learn":[0.2413828701],"iteration":802,"passed_time":37.54594885,"remaining_time":9.211148099},
{"learn":[0.2413718271],"iteration":803,"passed_time":37.59134954,"remaining_time":9.164060336},
{"learn":[0.2413673896],"iteration":804,"passed_time":37.63577925,"remaining_time":9.116741558},
{"learn":[0.2413604284],"iteration":805,"passed_time":37.68035232,"remaining_time":9.069464455},
{"learn":[0.2413530777],"iteration":806,"passed_time":37.72602113,"remaining_time":9.022456106},
{"learn":[0.2413412895],"iteration":807,"passed_time":37.77007279,"remaining_time":8.9750668},
{"learn":[0.2413315338],"iteration":808,"passed_time":37.815411,"remaining_time":8.927989495},
{"learn":[0.2413266559],"iteration":809,"passed_time":37.86078718,"remaining_time":8.880925388},
{"learn":[0.2413225571],"iteration":810,"passed_time":37.9062993,"remaining_time":8.833897124},
{"learn":[0.2413122085],"iteration":811,"passed_time":37.95505308,"remaining_time":8.787623128},
{"learn":[0.2413084146],"iteration":812,"passed_time":37.99875779,"remaining_time":8.740181682},
{"learn":[0.2413007252],"iteration":813,"passed_time":38.04466521,"remaining_time":8.693252739},
{"learn":[0.2412917147],"iteration":814,"passed_time":38.08821156,"remaining_time":8.645790353},
{"learn":[0.2412810782],"iteration":815,"passed_time":38.14175792,"remaining_time":8.600592472},
{"learn":[0.2412716273],"iteration":816,"passed_time":38.18591275,"remaining_time":8.553270543},
{"learn":[0.2412627692],"iteration":817,"passed_time":38.23316365,"remaining_time":8.506645214},
{"learn":[0.241255029],"iteration":818,"passed_time":38.27714903,"remaining_time":8.459296673},
{"learn":[0.2412434948],"iteration":819,"passed_time":38.32341297,"remaining_time":8.412456506},
{"learn":[0.2412391928],"iteration":820,"passed_time":38.36729673,"remaining_time":8.3650988},
{"learn":[0.2412322655],"iteration":821,"passed_time":38.41105976,"remaining_time":8.317723402},
{"learn":[0.2412249826],"iteration":822,"passed_time":38.45818722,"remaining_time":8.271080361},
{"learn":[0.2412113313],"iteration":823,"passed_time":38.50671742,"remaining_time":8.224735759},
{"learn":[0.2412059284],"iteration":824,"passed_time":38.55283876,"remaining_time":8.177874889},
{"learn":[0.2412012876],"iteration":825,"passed_time":38.59780909,"remaining_time":8.130773343},
{"learn":[0.2411976969],"iteration":826,"passed_time":38.64496374,"remaining_time":8.08413389},
{"learn":[0.2411905834],"iteration":827,"passed_time":38.68910036,"remaining_time":8.036866259},
{"learn":[0.2411841811],"iteration":828,"passed_time":38.73171754,"remaining_time":7.989292761},
{"learn":[0.2411787952],"iteration":829,"passed_time":38.77736184,"remaining_time":7.94235122},
{"learn":[0.2411713259],"iteration":830,"passed_time":38.82595526,"remaining_time":7.896012563},
{"learn":[0.2411644156],"iteration":831,"passed_time":38.86952339,"remaining_time":7.848653762},
{"learn":[0.2411567261],"iteration":832,"passed_time":38.91835392,"remaining_time":7.80235907},
{"learn":[0.2411461405],"iteration":833,"passed_time":38.9632685,"remaining_time":7.755278863},
{"learn":[0.2411406359],"iteration":834,"passed_time":39.01194684,"remaining_time":7.708947579},
{"learn":[0.2411298131],"iteration":835,"passed_time":39.06487991,"remaining_time":7.663445341},
{"learn":[0.2411238343],"iteration":836,"passed_time":39.10995391,"remaining_time":7.616394848},
{"learn":[0.2411148746],"iteration":837,"passed_time":39.15511319,"remaining_time":7.569365557},
{"learn":[0.2411039841],"iteration":838,"passed_time":39.19918264,"remaining_time":7.52213159},
{"learn":[0.2411000547],"iteration":839,"passed_time":39.24582669,"remaining_time":7.47539556},
{"learn":[0.2410936524],"iteration":840,"passed_time":39.2898677,"remaining_time":7.428167614},
{"learn":[0.2410896722],"iteration":841,"passed_time":39.33923966,"remaining_time":7.381947585},
{"learn":[0.2410858953],"iteration":842,"passed_time":39.38373763,"remaining_time":7.334812347},
{"learn":[0.2410735481],"iteration":843,"passed_time":39.42850266,"remaining_time":7.287732719},
{"learn":[0.2410579999],"iteration":844,"passed_time":39.47270994,"remaining_time":7.240556261},
{"learn":[0.2410498362],"iteration":845,"passed_time":39.52001497,"remaining_time":7.193950715},
{"learn":[0.2410399958],"iteration":846,"passed_time":39.56455765,"remaining_time":7.146844534},
{"learn":[0.2410303755],"iteration":847,"passed_time":39.60927715,"remaining_time":7.099776092},
{"learn":[0.2410208061],"iteration":848,"passed_time":39.65477355,"remaining_time":7.052851362},
{"learn":[0.2410147934],"iteration":849,"passed_time":39.69861809,"remaining_time":7.005638486},
{"learn":[0.2410092719],"iteration":850,"passed_time":39.74322382,"remaining_time":6.958566802},
{"learn":[0.2410034117],"iteration":851,"passed_time":39.78814176,"remaining_time":6.911555142},
{"learn":[0.2409893539],"iteration":852,"passed_time":39.83204221,"remaining_time":6.864373042},
{"learn":[0.2409856785],"iteration":853,"passed_time":39.87704588,"remaining_time":6.817387234},
{"learn":[0.2409815798],"iteration":854,"passed_time":39.92505901,"remaining_time":6.770916441},
{"learn":[0.2409739242],"iteration":855,"passed_time":39.97216757,"remaining_time":6.724289872},
{"learn":[0.2409717393],"iteration":856,"passed_time":40.0213216,"remaining_time":6.678003488},
{"learn":[0.2409658452],"iteration":857,"passed_time":40.06938572,"remaining_time":6.631530037},
{"learn":[0.240960798],"iteration":858,"passed_time":40.11452766,"remaining_time":6.584573225},
{"learn":[0.2409518721],"iteration":859,"passed_time":40.15841286,"remaining_time":6.537416047},
{"learn":[0.2409466047],"iteration":860,"passed_time":40.20412107,"remaining_time":6.490560777},
{"learn":[0.2409445892],"iteration":861,"passed_time":40.24870897,"remaining_time":6.443528815},
{"learn":[0.2409349012],"iteration":862,"passed_time":40.29266541,"remaining_time":6.396402272},
{"learn":[0.240921487],"iteration":863,"passed_time":40.33823487,"remaining_time":6.34953697},
{"learn":[0.2409174221],"iteration":864,"passed_time":40.38560136,"remaining_time":6.302955125},
{"learn":[0.2409106811],"iteration":865,"passed_time":40.43128494,"remaining_time":6.256111064},
{"learn":[0.2409012472],"iteration":866,"passed_time":40.47839547,"remaining_time":6.209488579},
{"learn":[0.2408985542],"iteration":867,"passed_time":40.52892748,"remaining_time":6.163385286},
{"learn":[0.2408943877],"iteration":868,"passed_time":40.57436054,"remaining_time":6.116503142},
{"learn":[0.2408902212],"iteration":869,"passed_time":40.62230465,"remaining_time":6.069999546},
{"learn":[0.2408865966],"iteration":870,"passed_time":40.66823877,"remaining_time":6.023194949},
{"learn":[0.2408802283],"iteration":871,"passed_time":40.71234325,"remaining_time":5.97612378},
{"learn":[0.2408768578],"iteration":872,"passed_time":40.75991428,"remaining_time":5.929563704},
{"learn":[0.2408716073],"iteration":873,"passed_time":40.8099358,"remaining_time":5.883354589},
{"learn":[0.2408674916],"iteration":874,"passed_time":40.85921706,"remaining_time":5.837031008},
{"learn":[0.2408626815],"iteration":875,"passed_time":40.89965026,"remaining_time":5.78944821},
{"learn":[0.2408569906],"iteration":876,"passed_time":40.95011619,"remaining_time":5.743288816},
{"learn":[0.2408447451],"iteration":877,"passed_time":40.99809849,"remaining_time":5.696774505},
{"learn":[0.2408405108],"iteration":878,"passed_time":41.04416797,"remaining_time":5.649993543},
{"learn":[0.2408332787],"iteration":879,"passed_time":41.08921218,"remaining_time":5.603074389},
{"learn":[0.2408283839],"iteration":880,"passed_time":41.13767192,"remaining_time":5.556620838},
{"learn":[0.2408236076],"iteration":881,"passed_time":41.18202249,"remaining_time":5.509612987},
{"learn":[0.2408163924],"iteration":882,"passed_time":41.22514073,"remaining_time":5.462447866},
{"learn":[0.2408117686],"iteration":883,"passed_time":41.26907027,"remaining_time":5.415398361},
{"learn":[0.240801979],"iteration":884,"passed_time":41.31587323,"remaining_time":5.36872929},
{"learn":[0.2407878873],"iteration":885,"passed_time":41.36040346,"remaining_time":5.321767488},
{"learn":[0.2407843305],"iteration":886,"passed_time":41.40981148,"remaining_time":5.275432579},
{"learn":[0.2407767258],"iteration":887,"passed_time":41.45558716,"remaining_time":5.228632615},
{"learn":[0.2407656659],"iteration":888,"passed_time":41.50073831,"remaining_time":5.181756976},
{"learn":[0.2407544535],"iteration":889,"passed_time":41.54538731,"remaining_time":5.134823151},
{"learn":[0.2407439864],"iteration":890,"passed_time":41.5897143,"remaining_time":5.08785506},
{"learn":[0.2407416321],"iteration":891,"passed_time":41.63682089,"remaining_time":5.041229435},
{"learn":[0.2407361106],"iteration":892,"passed_time":41.68151077,"remaining_time":4.99431316},
{"learn":[0.2407323506],"iteration":893,"passed_time":41.72550457,"remaining_time":4.947319334},
{"learn":[0.2407221714],"iteration":894,"passed_time":41.76910453,"remaining_time":4.900286006},
{"learn":[0.2407102985],"iteration":895,"passed_time":41.81402182,"remaining_time":4.853413247},
{"learn":[0.2407023381],"iteration":896,"passed_time":41.85786085,"remaining_time":4.806421034},
{"learn":[0.240695377],"iteration":897,"passed_time":41.90254924,"remaining_time":4.759532318},
{"learn":[0.2406927009],"iteration":898,"passed_time":41.95151791,"remaining_time":4.713129376},
{"learn":[0.2406787617],"iteration":899,"passed_time":41.99565393,"remaining_time":4.66618377},
{"learn":[0.2406742564],"iteration":900,"passed_time":42.0400772,"remaining_time":4.619275963},
{"learn":[0.2406695648],"iteration":901,"passed_time":42.08305676,"remaining_time":4.57221681},
{"learn":[0.2406647208],"iteration":902,"passed_time":42.12793172,"remaining_time":4.525370295},
{"learn":[0.24065903],"iteration":903,"passed_time":42.1741809,"remaining_time":4.478674078},
{"learn":[0.240651764],"iteration":904,"passed_time":42.21991761,"remaining_time":4.431925053},
{"learn":[0.240646378],"iteration":905,"passed_time":42.27035046,"remaining_time":4.3856655},
{"learn":[0.2406410936],"iteration":906,"passed_time":42.32662828,"remaining_time":4.339996064},
{"learn":[0.2406392136],"iteration":907,"passed_time":42.37601799,"remaining_time":4.293605347},
{"learn":[0.2406306434],"iteration":908,"passed_time":42.42439235,"remaining_time":4.247106385},
{"learn":[0.2406176019],"iteration":909,"passed_time":42.46975806,"remaining_time":4.200305742},
{"learn":[0.2406113521],"iteration":910,"passed_time":42.51829089,"remaining_time":4.153817661},
{"learn":[0.2405969725],"iteration":911,"passed_time":42.56607174,"remaining_time":4.107252536},
{"learn":[0.2405890968],"iteration":912,"passed_time":42.61375355,"remaining_time":4.060675311},
{"learn":[0.2405809162],"iteration":913,"passed_time":42.66039911,"remaining_time":4.013998166},
{"learn":[0.2405733114],"iteration":914,"passed_time":42.70645687,"remaining_time":3.967266485},
{"learn":[0.2405651647],"iteration":915,"passed_time":42.75124408,"remaining_time":3.920419763},
{"learn":[0.2405616248],"iteration":916,"passed_time":42.79785292,"remaining_time":3.873742413},
{"learn":[0.240551073],"iteration":917,"passed_time":42.84378789,"remaining_time":3.827005018},
{"learn":[0.2405485325],"iteration":918,"passed_time":42.89638895,"remaining_time":3.780856915},
{"learn":[0.2405452975],"iteration":919,"passed_time":42.94285608,"remaining_time":3.734161398},
{"learn":[0.2405348812],"iteration":920,"passed_time":42.99109423,"remaining_time":3.687618289},
{"learn":[0.2405231607],"iteration":921,"passed_time":43.03712961,"remaining_time":3.640885151},
{"learn":[0.2405144042],"iteration":922,"passed_time":43.08293817,"remaining_time":3.594134604},
{"learn":[0.2405052921],"iteration":923,"passed_time":43.1282982,"remaining_time":3.547349202},
{"learn":[0.2404983479],"iteration":924,"passed_time":43.17428064,"remaining_time":3.500617349},
{"learn":[0.240489168],"iteration":925,"passed_time":43.22078182,"remaining_time":3.453928568},
{"learn":[0.2404842393],"iteration":926,"passed_time":43.26882723,"remaining_time":3.407361799},
{"learn":[0.2404764821],"iteration":927,"passed_time":43.3151646,"remaining_time":3.360659323},
{"learn":[0.2404713163],"iteration":928,"passed_time":43.36064375,"remaining_time":3.313892041},
{"learn":[0.2404655069],"iteration":929,"passed_time":43.40466574,"remaining_time":3.267017851},
{"learn":[0.2404579699],"iteration":930,"passed_time":43.45250196,"remaining_time":3.220432476},
{"learn":[0.2404509749],"iteration":931,"passed_time":43.49626261,"remaining_time":3.173547057},
{"learn":[0.2404456905],"iteration":932,"passed_time":43.5412379,"remaining_time":3.126755562},
{"learn":[0.240438018],"iteration":933,"passed_time":43.58582769,"remaining_time":3.079940715},
{"learn":[0.2404332417],"iteration":934,"passed_time":43.63285161,"remaining_time":3.033299845},
{"learn":[0.2404299729],"iteration":935,"passed_time":43.68104861,"remaining_time":2.986738367},
{"learn":[0.2404228763],"iteration":936,"passed_time":43.72540009,"remaining_time":2.939914841},
{"learn":[0.2404115623],"iteration":937,"passed_time":43.77064014,"remaining_time":2.893155318},
{"learn":[0.2404017726],"iteration":938,"passed_time":43.81486668,"remaining_time":2.846333192},
{"learn":[0.2403897812],"iteration":939,"passed_time":43.858942,"remaining_time":2.799506936},
{"learn":[0.24038553],"iteration":940,"passed_time":43.90252885,"remaining_time":2.7526559},
{"learn":[0.2403807707],"iteration":941,"passed_time":43.94820133,"remaining_time":2.705940209},
{"learn":[0.2403723868],"iteration":942,"passed_time":43.99190043,"remaining_time":2.659107449},
{"learn":[0.2403654595],"iteration":943,"passed_time":44.0370265,"remaining_time":2.612365979},
{"learn":[0.2403595485],"iteration":944,"passed_time":44.08503946,"remaining_time":2.565795947},
{"learn":[0.2403524519],"iteration":945,"passed_time":44.1296173,"remaining_time":2.51902678},
{"learn":[0.2403462529],"iteration":946,"passed_time":44.179322,"remaining_time":2.472549172},
{"learn":[0.2403407822],"iteration":947,"passed_time":44.22376392,"remaining_time":2.42577608},
{"learn":[0.2403368359],"iteration":948,"passed_time":44.27053003,"remaining_time":2.379132804},
{"learn":[0.2403332113],"iteration":949,"passed_time":44.31254609,"remaining_time":2.332239268},
{"learn":[0.2403264026],"iteration":950,"passed_time":44.36314316,"remaining_time":2.285798123},
{"learn":[0.2403213046],"iteration":951,"passed_time":44.40343668,"remaining_time":2.23882874},
{"learn":[0.2403151733],"iteration":952,"passed_time":44.45394662,"remaining_time":2.192377221},
{"learn":[0.2403088558],"iteration":953,"passed_time":44.50562292,"remaining_time":2.145973432},
{"learn":[0.2403008107],"iteration":954,"passed_time":44.55092647,"remaining_time":2.099258315},
{"learn":[0.2402962038],"iteration":955,"passed_time":44.59763125,"remaining_time":2.052610643},
{"learn":[0.2402861601],"iteration":956,"passed_time":44.64316756,"remaining_time":2.00591035},
{"learn":[0.2402790127],"iteration":957,"passed_time":44.68781354,"remaining_time":1.959173454},
{"learn":[0.2402691214],"iteration":958,"passed_time":44.73251597,"remaining_time":1.912443331},
{"learn":[0.2402568082],"iteration":959,"passed_time":44.77894274,"remaining_time":1.865789281},
{"learn":[0.2402516762],"iteration":960,"passed_time":44.82347735,"remaining_time":1.819058914},
{"learn":[0.2402455789],"iteration":961,"passed_time":44.86897237,"remaining_time":1.77237105},
{"learn":[0.2402338076],"iteration":962,"passed_time":44.91411402,"remaining_time":1.725672086},
{"learn":[0.2402231881],"iteration":963,"passed_time":44.95919684,"remaining_time":1.678974156},
{"learn":[0.2402203426],"iteration":964,"passed_time":45.00684448,"remaining_time":1.632372598},
{"learn":[0.2402154986],"iteration":965,"passed_time":45.05135256,"remaining_time":1.585658372},
{"learn":[0.2402058784],"iteration":966,"passed_time":45.0951766,"remaining_time":1.538925365},
{"learn":[0.2401961226],"iteration":967,"passed_time":45.14188733,"remaining_time":1.492293796},
{"learn":[0.240189009],"iteration":968,"passed_time":45.19329505,"remaining_time":1.445812329},
{"learn":[0.2401837077],"iteration":969,"passed_time":45.23737198,"remaining_time":1.399093979},
{"learn":[0.2401742738],"iteration":970,"passed_time":45.28183797,"remaining_time":1.352392689},
{"learn":[0.2401699379],"iteration":971,"passed_time":45.32864576,"remaining_time":1.305763458},
{"learn":[0.2401596909],"iteration":972,"passed_time":45.37490446,"remaining_time":1.259118623},
{"learn":[0.240150511],"iteration":973,"passed_time":45.41970282,"remaining_time":1.212435599},
{"learn":[0.2401445661],"iteration":974,"passed_time":45.46443136,"remaining_time":1.16575465},
{"learn":[0.2401395527],"iteration":975,"passed_time":45.51030484,"remaining_time":1.119105857},
{"learn":[0.2401355895],"iteration":976,"passed_time":45.55781539,"remaining_time":1.072497189},
{"learn":[0.24013061],"iteration":977,"passed_time":45.59780125,"remaining_time":1.025717411},
{"learn":[0.240126037],"iteration":978,"passed_time":45.64224715,"remaining_time":0.9790471809},
{"learn":[0.2401182798],"iteration":979,"passed_time":45.68707523,"remaining_time":0.9323892904},
{"learn":[0.2401115727],"iteration":980,"passed_time":45.73082191,"remaining_time":0.8857141858},
{"learn":[0.2401089136],"iteration":981,"passed_time":45.78027454,"remaining_time":0.8391496351},
{"learn":[0.2401018847],"iteration":982,"passed_time":45.82397357,"remaining_time":0.7924797057},
{"learn":[0.2400952453],"iteration":983,"passed_time":45.86694836,"remaining_time":0.7458040384},
{"learn":[0.2400878946],"iteration":984,"passed_time":45.91131104,"remaining_time":0.699157021},
{"learn":[0.2400798665],"iteration":985,"passed_time":45.9596748,"remaining_time":0.6525714474},
{"learn":[0.2400759032],"iteration":986,"passed_time":46.00285548,"remaining_time":0.6059140033},
{"learn":[0.2400631665],"iteration":987,"passed_time":46.04712214,"remaining_time":0.5592767871},
{"learn":[0.2400545794],"iteration":988,"passed_time":46.09268138,"remaining_time":0.5126587413},
{"learn":[0.240048499],"iteration":989,"passed_time":46.13719083,"remaining_time":0.4660322306},
{"learn":[0.2400402845],"iteration":990,"passed_time":46.18200404,"remaining_time":0.4194127511},
{"learn":[0.2400292754],"iteration":991,"passed_time":46.22655512,"remaining_time":0.3727947993},
{"learn":[0.2400241943],"iteration":992,"passed_time":46.27021718,"remaining_time":0.3261747434},
{"learn":[0.2400179445],"iteration":993,"passed_time":46.31458227,"remaining_time":0.2795648829},
{"learn":[0.2400019728],"iteration":994,"passed_time":46.35867785,"remaining_time":0.2329581801},
{"learn":[0.2399925389],"iteration":995,"passed_time":46.40304074,"remaining_time":0.1863575933},
{"learn":[0.2399850357],"iteration":996,"passed_time":46.44725777,"remaining_time":0.1397610565},
{"learn":[0.2399770923],"iteration":997,"passed_time":46.49209852,"remaining_time":0.09317053812},
{"learn":[0.239972858],"iteration":998,"passed_time":46.53682744,"remaining_time":0.04658341085},
{"learn":[0.2399676075],"iteration":999,"passed_time":46.58151951,"remaining_time":0}
]}